Assignments/Lab06-Incubator-Controller/rtl/incubator_pkg.vh
// Shared constants for the incubator controller.
//
// Temperature representation
// --------------------------
// The sensor delivers the container temperature as an 8-bit number covering
// -10 .. +60 degrees Celsius. An 8-bit SIGNED two's-complement code is used,
// so the value read from the sensor is the temperature in degrees directly:
//
//     8'shF6 = -10   (coldest)
//     8'sh00 =   0
//     8'sh3C = +60   (hottest)
//
// This keeps every comparison in the design a plain signed comparison
// against a decimal threshold, which is exactly how the state diagrams in
// the lab sheet are written (T<15, T>35, ...).
`ifndef INCUBATOR_PKG_VH
`define INCUBATOR_PKG_VH

// Sensor range limits
`define TEMP_MIN  (-8'sd10)
`define TEMP_MAX  ( 8'sd60)

// --- main FSM thresholds (left-hand state diagram) ---
`define TH_HEAT_ON    ( 8'sd15)   // S1 -> S3 when T < 15
`define TH_HEAT_OFF   ( 8'sd30)   // S3 -> S1 when T > 30
`define TH_COOL_OFF   ( 8'sd25)   // S2 -> S1 when T < 25
`define TH_COOL_ON    ( 8'sd35)   // S1 -> S2 when T > 35

// --- fan-speed FSM thresholds (right-hand state diagram) ---
`define TH_FAN_OUT    ( 8'sd25)   // F_S1 -> OUT  when T < 25
`define TH_FAN_IN     ( 8'sd35)   // OUT  -> F_S1 when T > 35
`define TH_FAN_DOWN1  ( 8'sd35)   // F_S2 -> F_S1 when T < 35
`define TH_FAN_UP1    ( 8'sd40)   // F_S1 -> F_S2 when T > 40
`define TH_FAN_DOWN2  ( 8'sd40)   // F_S3 -> F_S2 when T < 40
`define TH_FAN_UP2    ( 8'sd45)   // F_S2 -> F_S3 when T > 45

// --- cooler rotational speed encoding (RPS) ---
`define CRS_OFF  (4'd0)
`define CRS_4    (4'd4)
`define CRS_6    (4'd6)
`define CRS_8    (4'd8)

`endif

Assignments/Lab06-Incubator-Controller/rtl/seven_seg_decoder.v
// Binary -> seven-segment decoder, common-anode (0 lights a segment).
// Bit order is {g,f,e,d,c,b,a}. Only the digits this design can produce
// (0, 4, 6, 8) really matter, but the full hex table is provided so the
// module is reusable and never emits an undefined pattern.
module seven_seg_decoder (
    input  wire [3:0] value,
    output reg  [6:0] seg
);
    always @(*) begin
        case (value)
            4'h0: seg = 7'b1000000;
            4'h1: seg = 7'b1111001;
            4'h2: seg = 7'b0100100;
            4'h3: seg = 7'b0110000;
            4'h4: seg = 7'b0011001;
            4'h5: seg = 7'b0010010;
            4'h6: seg = 7'b0000010;
            4'h7: seg = 7'b1111000;
            4'h8: seg = 7'b0000000;
            4'h9: seg = 7'b0010000;
            4'hA: seg = 7'b0001000;
            4'hB: seg = 7'b0000011;
            4'hC: seg = 7'b1000110;
            4'hD: seg = 7'b0100001;
            4'hE: seg = 7'b0000110;
            4'hF: seg = 7'b0001110;
            default: seg = 7'b1111111;   // blank
        endcase
    end
endmodule

Assignments/Lab06-Incubator-Controller/rtl/fan_fsm.v
`include "incubator_pkg.vh"

// Cooler fan-speed controller — RIGHT-HAND state diagram.
//
//                        T<40
//              ┌───────────────────────┐
//              ▼                       │
//        ┌──────────┐            ┌──────────┐
//        │    S3    │   T>45     │    S2    │
//        │ CRS=8RPS │◄───────────│ CRS=6RPS │
//        └──────────┘            └──────────┘
//                                  ▲      │ T<35
//                             T>40 │      ▼
//        ┌──────────┐            ┌──────────┐
//        │   OUT    │   T>35     │    S1    │
//        │ (idle)   │───────────►│ CRS=4RPS │
//        └──────────┘◄───────────└──────────┘
//                        T<25
//
// Enable rule (from the lab text)
// ------------------------------
// This machine is active ONLY while the main FSM sits in its S2 state, i.e.
// while the cooler is actually running — setting a rotation speed for a
// cooler that is switched off is meaningless. The lab sheet states that when
// the main FSM is not in S2 this machine "enters its OUT state", so `enable`
// going low forces OUT rather than freezing the current state. A later
// re-entry into S2 therefore always restarts from OUT.
//
// As in the main FSM, a temperature that satisfies no outgoing guard leaves
// the state unchanged.
module fan_fsm (
    input  wire               Clk,
    input  wire               RstN,      // async, active-low
    input  wire               tick,      // once-per-minute sample strobe
    input  wire signed [7:0]  temp,
    input  wire               enable,    // 1 only while main FSM is in S2

    output wire [3:0]         crs,       // cooler rotational speed, in RPS
    output wire [1:0]         state      // exposed for debug/waveforms
);
    localparam [1:0] OUT  = 2'd0,   // fan idle (cooler is off)
                     F_S1 = 2'd1,   // 4 RPS
                     F_S2 = 2'd2,   // 6 RPS
                     F_S3 = 2'd3;   // 8 RPS

    reg [1:0] cur, nxt;

    assign state = cur;

    // Moore output: the speed is a property of the state alone.
    // OUT reports 0 RPS because the fan is not turning at all then.
    assign crs = (cur == F_S1) ? `CRS_4 :
                 (cur == F_S2) ? `CRS_6 :
                 (cur == F_S3) ? `CRS_8 : `CRS_OFF;

    always @(*) begin
        nxt = cur;                        // default: hold
        case (cur)
            OUT:  if (temp > `TH_FAN_IN)    nxt = F_S1;  // T > 35
            F_S1: begin
                if      (temp > `TH_FAN_UP1) nxt = F_S2; // T > 40
                else if (temp < `TH_FAN_OUT) nxt = OUT;  // T < 25
            end
            F_S2: begin
                if      (temp > `TH_FAN_UP2)   nxt = F_S3; // T > 45
                else if (temp < `TH_FAN_DOWN1) nxt = F_S1; // T < 35
            end
            F_S3: if (temp < `TH_FAN_DOWN2)  nxt = F_S2;  // T < 40
            default:                         nxt = OUT;
        endcase
    end

    always @(posedge Clk or negedge RstN) begin
        if (!RstN)       cur <= OUT;
        else if (!enable) cur <= OUT;     // cooler off => park in OUT
        else if (tick)    cur <= nxt;
    end
endmodule

Assignments/Lab06-Incubator-Controller/rtl/main_fsm.v
`include "incubator_pkg.vh"

// Incubator main controller — LEFT-HAND state diagram.
//
//                    T<25
//         ┌──────────────────────────┐
//         ▼                          │
//   ┌──────────┐   T>35        ┌──────────┐
//   │    S2    │◄──────────────│    S1    │◄── reset
//   │ Heater:  │               │ Heater:  │
//   │   OFF    │               │   OFF    │
//   │ Cooler:  │               │ Cooler:  │
//   │   ON     │               │   OFF    │
//   └──────────┘               └──────────┘
//                                 ▲     │ T<15
//                            T>30 │     ▼
//                              ┌──────────┐
//                              │    S3    │
//                              │ Heater:ON│
//                              │ Cooler:  │
//                              │   OFF    │
//                              └──────────┘
//
// The diagram labels only the transitions listed above. For any temperature
// that does not satisfy the outgoing guard of the current state, the machine
// HOLDS its state — that is what gives the controller its hysteresis (the
// 15..35 dead band around S1) and stops the heater and cooler chattering on
// and off around a single set point.
//
// `tick` is the once-per-minute sample strobe: the lab specifies that the
// temperature is read from the sensor once every minute, so the FSM advances
// only on a tick, not on every clock.
module main_fsm (
    input  wire               Clk,
    input  wire               RstN,        // async, active-low
    input  wire               tick,        // 1-clock strobe, once per minute
    input  wire signed [7:0]  temp,        // degrees C, -10 .. +60

    output wire               heater,      // 1 = heater energised
    output wire               cooler,      // 1 = cooler energised
    output wire [1:0]         state,       // current state (debug/waveforms)
    output wire               cooler_next  // 1 if THIS tick moves us into S2
);
    localparam [1:0] S1 = 2'd0,   // both off  (reset state)
                     S2 = 2'd1,   // cooler on
                     S3 = 2'd2;   // heater on

    reg [1:0] cur, nxt;

    assign state  = cur;
    // Moore outputs: they depend on the state alone.
    assign heater = (cur == S3);
    assign cooler = (cur == S2);

    // The state this FSM will hold *after* the current tick. The fan machine
    // is gated on this rather than on `cooler`, so that on the very tick that
    // leaves S2 the fan parks in OUT instead of taking one more step with a
    // cooler that is already switching off.
    assign cooler_next = (nxt == S2);

    always @(*) begin
        nxt = cur;                       // default: hold (see note above)
        case (cur)
            S1: begin
                // Only one of these can be true: 15 < 35, so the guards are
                // mutually exclusive and the priority here is cosmetic.
                if (temp > `TH_COOL_ON)       nxt = S2;   // T > 35 -> cool
                else if (temp < `TH_HEAT_ON)  nxt = S3;   // T < 15 -> heat
            end
            S2: if (temp < `TH_COOL_OFF)      nxt = S1;   // T < 25 -> off
            S3: if (temp > `TH_HEAT_OFF)      nxt = S1;   // T > 30 -> off
            default:                          nxt = S1;
        endcase
    end

    always @(posedge Clk or negedge RstN) begin
        if (!RstN)     cur <= S1;
        else if (tick) cur <= nxt;
    end
endmodule

Assignments/Lab06-Incubator-Controller/rtl/tick_gen.v
// Once-per-minute sample strobe.
//
// The lab specifies that the temperature is read from the sensor once every
// minute. Rather than bury a fixed constant in the design, the divider ratio
// is a parameter: synthesis uses the real value (e.g. 50 MHz x 60 s =
// 3_000_000_000, or a smaller number if the board clock is divided first),
// while simulation overrides it with a tiny value so a testbench does not
// have to simulate minutes of wall-clock time.
//
// `tick` is a single-clock-wide pulse, so the FSMs advance exactly one step
// per sample period.
module tick_gen #(
    parameter integer DIVIDE = 60_000_000   // clocks between samples
) (
    input  wire Clk,
    input  wire RstN,      // async, active-low
    output reg  tick
);
    localparam integer CNT_W = (DIVIDE <= 1) ? 1 : $clog2(DIVIDE);

    reg [CNT_W-1:0] cnt;

    always @(posedge Clk or negedge RstN) begin
        if (!RstN) begin
            cnt  <= {CNT_W{1'b0}};
            tick <= 1'b0;
        end else if (cnt == DIVIDE - 1) begin
            cnt  <= {CNT_W{1'b0}};
            tick <= 1'b1;                 // one clock wide
        end else begin
            cnt  <= cnt + 1'b1;
            tick <= 1'b0;
        end
    end
endmodule

Assignments/Lab06-Incubator-Controller/rtl/incubator_controller.v
`include "incubator_pkg.vh"

// Incubator digital control unit — TOP LEVEL.
//
// The lab asks for the *digital control unit* only: the sensor, heater and
// cooler are outside the chip. The temperature therefore arrives as an
// 8-bit number and the actuators are represented by output signals which,
// on the FPGA board, drive LEDs and a seven-segment display instead of real
// hardware.
//
//        temp[7:0] ─┬─────────────────────────────► main_fsm ──► heater
//                   │                                  │         cooler
//                   │                                  │ (state==S2)
//                   │                                  ▼
//                   └─────────────────────────────► fan_fsm ───► crs[3:0]
//                                                  (enable)
//
//   tick_gen ──── tick (once per minute) ──► both FSMs
//
// Board-friendly outputs
// ----------------------
//   heater / cooler : drive two LEDs.
//   crs             : the fan speed in RPS as a plain number (0/4/6/8), ready
//                     for a seven-segment decoder.
//   crs_seg         : the same value already encoded for a common-anode
//                     seven-segment digit, so the design can be dropped onto
//                     the board without extra glue.
module incubator_controller #(
    // Clocks between temperature samples. Override in simulation.
    parameter integer TICK_DIVIDE = 60_000_000
) (
    input  wire               Clk,
    input  wire               RstN,          // async, active-low
    input  wire signed [7:0]  temp,          // from the sensor, -10..+60 C

    output wire               heater,        // LED / heater enable
    output wire               cooler,        // LED / cooler enable
    output wire [3:0]         crs,           // cooler speed in RPS (0/4/6/8)
    output wire [6:0]         crs_seg,       // seven-segment (common anode)
    output wire [1:0]         main_state,    // debug / waveform visibility
    output wire [1:0]         fan_state,
    output wire               tick
);
    wire        cooler_next;
    wire [1:0]  m_state;

    tick_gen #(.DIVIDE(TICK_DIVIDE)) u_tick (
        .Clk(Clk), .RstN(RstN), .tick(tick)
    );

    main_fsm u_main (
        .Clk         (Clk),
        .RstN        (RstN),
        .tick        (tick),
        .temp        (temp),
        .heater      (heater),
        .cooler      (cooler),
        .state       (m_state),
        .cooler_next (cooler_next)
    );

    // The fan machine runs only while the cooler is on. It is gated on the
    // main FSM's NEXT state so that the tick which switches the cooler off
    // also parks the fan in OUT -- otherwise the speed display would show a
    // turning fan for one whole sample period after the cooler stopped.

    fan_fsm u_fan (
        .Clk    (Clk),
        .RstN   (RstN),
        .tick   (tick),
        .temp   (temp),
        .enable (cooler_next),
        .crs    (crs),
        .state  (fan_state)
    );

    assign main_state = m_state;

    seven_seg_decoder u_seg (.value(crs), .seg(crs_seg));
endmodule

Assignments/Lab06-Incubator-Controller/tb/tb_incubator_wave.v
`timescale 1ns/1ps

// Presentation-friendly demo that dumps a VCD covering a full thermal cycle:
// cold (heater on) -> dead band -> hot (cooler on, fan climbing 4->6->8 RPS)
// -> cooling back down the ladder -> cooler off (fan parks at 0).
`ifndef VCD_FILE
`define VCD_FILE "waves/incubator.vcd"
`endif

module tb_incubator_wave;
    localparam integer TICKDIV = 4;

    reg               Clk, RstN;
    reg signed [7:0]  temp;
    wire              heater, cooler, tick;
    wire [3:0]        crs;
    wire [6:0]        crs_seg;
    wire [1:0]        main_state, fan_state;

    incubator_controller #(.TICK_DIVIDE(TICKDIV)) dut (
        .Clk(Clk), .RstN(RstN), .temp(temp),
        .heater(heater), .cooler(cooler), .crs(crs), .crs_seg(crs_seg),
        .main_state(main_state), .fan_state(fan_state), .tick(tick)
    );

    initial Clk = 1'b0;
    always #5 Clk = ~Clk;

    task automatic sample;
        input signed [7:0] T;
        begin
            temp = T;
            @(posedge tick);
            @(posedge Clk);
        end
    endtask

    initial begin
        $dumpfile(`VCD_FILE);
        $dumpvars(0, tb_incubator_wave);

        RstN = 1'b1; temp = 8'sd20;
        @(negedge Clk); RstN = 1'b0;
        @(negedge Clk); @(negedge Clk); RstN = 1'b1;

        sample(8'sd20);   // dead band: everything off
        sample(8'sd12);   // T<15  -> heater ON  (S3)
        sample(8'sd20);   // 15..30: heater stays on (hysteresis)
        sample(8'sd33);   // T>30  -> heater OFF (S1)
        sample(8'sd38);   // T>35  -> cooler ON  (S2), fan starts at 4 RPS
        sample(8'sd42);   // T>40  -> 6 RPS
        sample(8'sd47);   // T>45  -> 8 RPS
        sample(8'sd38);   // T<40  -> 6 RPS
        sample(8'sd33);   // T<35  -> 4 RPS
        sample(8'sd22);   // T<25  -> cooler OFF, fan parks at 0 RPS
        sample(8'sd22);   // stays off

        #40;
        $display("Wrote VCD: %s", `VCD_FILE);
        $finish;
    end
endmodule

Assignments/Lab06-Incubator-Controller/waves/incubator.vcd
$date
	Sat Aug 22 15:13:01 2026
$end
$version
	Icarus Verilog
$end
$timescale
	1ps
$end
$scope module tb_incubator_wave $end
$var wire 1 ! tick $end
$var wire 2 " main_state [1:0] $end
$var wire 1 # heater $end
$var wire 2 $ fan_state [1:0] $end
$var wire 7 % crs_seg [6:0] $end
$var wire 4 & crs [3:0] $end
$var wire 1 ' cooler $end
$var parameter 32 ( TICKDIV $end
$var reg 1 ) Clk $end
$var reg 1 * RstN $end
$var reg 8 + temp [7:0] $end
$scope module dut $end
$var wire 1 ) Clk $end
$var wire 1 * RstN $end
$var wire 2 , main_state [1:0] $end
$var wire 8 - temp [7:0] $end
$var wire 1 ! tick $end
$var wire 2 . m_state [1:0] $end
$var wire 1 # heater $end
$var wire 2 / fan_state [1:0] $end
$var wire 7 0 crs_seg [6:0] $end
$var wire 4 1 crs [3:0] $end
$var wire 1 2 cooler_next $end
$var wire 1 ' cooler $end
$var parameter 32 3 TICK_DIVIDE $end
$scope module u_fan $end
$var wire 1 ) Clk $end
$var wire 1 * RstN $end
$var wire 2 4 state [1:0] $end
$var wire 8 5 temp [7:0] $end
$var wire 1 ! tick $end
$var wire 1 2 enable $end
$var wire 4 6 crs [3:0] $end
$var parameter 2 7 F_S1 $end
$var parameter 2 8 F_S2 $end
$var parameter 2 9 F_S3 $end
$var parameter 2 : OUT $end
$var reg 2 ; cur [1:0] $end
$var reg 2 < nxt [1:0] $end
$upscope $end
$scope module u_main $end
$var wire 1 ) Clk $end
$var wire 1 * RstN $end
$var wire 2 = state [1:0] $end
$var wire 8 > temp [7:0] $end
$var wire 1 ! tick $end
$var wire 1 # heater $end
$var wire 1 2 cooler_next $end
$var wire 1 ' cooler $end
$var parameter 2 ? S1 $end
$var parameter 2 @ S2 $end
$var parameter 2 A S3 $end
$var reg 2 B cur [1:0] $end
$var reg 2 C nxt [1:0] $end
$upscope $end
$scope module u_seg $end
$var wire 4 D value [3:0] $end
$var reg 7 E seg [6:0] $end
$upscope $end
$scope module u_tick $end
$var wire 1 ) Clk $end
$var wire 1 * RstN $end
$var parameter 32 F CNT_W $end
$var parameter 32 G DIVIDE $end
$var reg 2 H cnt [1:0] $end
$var reg 1 ! tick $end
$upscope $end
$upscope $end
$scope task sample $end
$upscope $end
$upscope $end
$enddefinitions $end
$comment Show the parameter values. $end
$dumpall
b100 G
b10 F
b10 A
b1 @
b0 ?
b0 :
b11 9
b10 8
b1 7
b100 3
b100 (
$end
#0
$dumpvars
bx H
b1111111 E
bx0 D
b0 C
bx B
b10100 >
bx =
b0 <
bx ;
bx0 6
b10100 5
bx 4
02
bx0 1
b1111111 0
bx /
bx .
b10100 -
bx ,
b10100 +
1*
0)
x'
bx0 &
b1111111 %
bx $
x#
bx "
x!
$end
#5000
b1000000 %
b1000000 0
b1000000 E
b0 &
b0 1
b0 6
b0 D
0!
b0 $
b0 /
b0 4
b0 ;
1)
#10000
0#
0'
b0 "
b0 ,
b0 .
b0 =
b0 B
b0 H
0*
0)
#15000
1)
#20000
0)
#25000
1)
#30000
1*
0)
#35000
b1 H
1)
#40000
0)
#45000
b10 H
1)
#50000
0)
#55000
b11 H
1)
#60000
0)
#65000
1!
b0 H
1)
#70000
0)
#75000
0!
b1 H
b10 C
b1100 +
b1100 -
b1100 5
b1100 >
1)
#80000
0)
#85000
b10 H
1)
#90000
0)
#95000
b11 H
1)
#100000
0)
#105000
1!
b0 H
1)
#110000
0)
#115000
0!
b1 H
1#
b10 "
b10 ,
b10 .
b10 =
b10 B
b10 C
b10100 +
b10100 -
b10100 5
b10100 >
1)
#120000
0)
#125000
b10 H
1)
#130000
0)
#135000
b11 H
1)
#140000
0)
#145000
1!
b0 H
1)
#150000
0)
#155000
0!
b1 H
b0 C
b100001 +
b100001 -
b100001 5
b100001 >
1)
#160000
0)
#165000
b10 H
1)
#170000
0)
#175000
b11 H
1)
#180000
0)
#185000
1!
b0 H
1)
#190000
0)
#195000
12
0!
b1 H
0#
b0 "
b0 ,
b0 .
b0 =
b0 B
b1 <
b1 C
b100110 +
b100110 -
b100110 5
b100110 >
1)
#200000
0)
#205000
b10 H
1)
#210000
0)
#215000
b11 H
1)
#220000
0)
#225000
1!
b0 H
1)
#230000
0)
#235000
b11001 %
b11001 0
b11001 E
b100 &
b100 1
b100 6
b100 D
0!
b1 H
1'
b1 "
b1 ,
b1 .
b1 =
b1 B
b1 $
b1 /
b1 4
b1 ;
b10 <
12
b1 C
b101010 +
b101010 -
b101010 5
b101010 >
1)
#240000
0)
#245000
b10 H
1)
#250000
0)
#255000
b11 H
1)
#260000
0)
#265000
1!
b0 H
1)
#270000
0)
#275000
b10 %
b10 0
b10 E
b110 &
b110 1
b110 6
b110 D
0!
b1 H
b10 $
b10 /
b10 4
b10 ;
b11 <
b101111 +
b101111 -
b101111 5
b101111 >
1)
#280000
0)
#285000
b10 H
1)
#290000
0)
#295000
b11 H
1)
#300000
0)
#305000
1!
b0 H
1)
#310000
0)
#315000
b0 %
b0 0
b0 E
b1000 &
b1000 1
b1000 6
b1000 D
0!
b1 H
b11 $
b11 /
b11 4
b11 ;
b10 <
b100110 +
b100110 -
b100110 5
b100110 >
1)
#320000
0)
#325000
b10 H
1)
#330000
0)
#335000
b11 H
1)
#340000
0)
#345000
1!
b0 H
1)
#350000
0)
#355000
b10 %
b10 0
b10 E
b110 &
b110 1
b110 6
b110 D
0!
b1 H
b10 $
b10 /
b10 4
b10 ;
b1 <
b100001 +
b100001 -
b100001 5
b100001 >
1)
#360000
0)
#365000
b10 H
1)
#370000
0)
#375000
b11 H
1)
#380000
0)
#385000
1!
b0 H
1)
#390000
0)
#395000
b11001 %
b11001 0
b11001 E
b100 &
b100 1
b100 6
b100 D
0!
b1 H
b1 $
b1 /
b1 4
b1 ;
b0 <
02
b0 C
b10110 +
b10110 -
b10110 5
b10110 >
1)
#400000
0)
#405000
b1000000 %
b1000000 0
b1000000 E
b0 &
b0 1
b0 6
b0 D
b0 $
b0 /
b0 4
b0 ;
b10 H
1)
#410000
0)
#415000
b11 H
1)
#420000
0)
#425000
1!
b0 H
1)
#430000
0)
#435000
0!
b1 H
0'
b0 "
b0 ,
b0 .
b0 =
b0 B
1)
#440000
0)
#445000
b10 H
1)
#450000
0)
#455000
b11 H
1)
#460000
0)
#465000
1!
b0 H
1)
#470000
0)
#475000
0!
b1 H
1)
#480000
0)
#485000
b10 H
1)
#490000
0)
#495000
b11 H
1)
#500000
0)
#505000
1!
b0 H
1)
#510000
0)
#515000
0!
b1 H
1)
