Assignments/Lab07-UART/rtl/uart_pkg.vh
// Shared parameters for the UART transmitter / receiver pair.
//
// Frame layout (exactly as specified in the lab sheet)
// ---------------------------------------------------
// The line idles HIGH. One character is 10 bit-times long:
//
//        +-------+--------+----+----+----+----+----+----+----+-------+
//   idle | START | PARITY | D6 | D5 | D4 | D3 | D2 | D1 | D0 | STOP  | idle
//        +-------+--------+----+----+----+----+----+----+----+-------+
//          1 bit   1 bit   <--------- 7 data bits ---------->  1 bit
//
// Two points differ from a "textbook" 8N1 UART and both come straight from
// the lab sheet:
//
//   1. The parity bit is sent BEFORE the data, not after it. A transmitter
//      therefore has to know the whole character before it starts shifting,
//      which is why the data is loaded in parallel and the parity is computed
//      combinationally at load time.
//
//   2. The payload is 7 bits (ASCII), and the receiver stores the 8 bits that
//      follow the start bit -- parity plus data -- into one 8-bit register.
//      Sending the data MSB first makes that register come out as
//      {parity, D6..D0}, i.e. the ASCII code sits in the low 7 bits with no
//      bit reversal anywhere in the design.
`ifndef UART_PKG_VH
`define UART_PKG_VH

`define UART_DATA_BITS   7      // ASCII payload
`define UART_FRAME_BITS  10     // start + parity + 7 data + stop
`define UART_RX_REG_BITS 8      // {parity, D6..D0}

// Number of oversampling ticks per bit time. 16x is the usual choice: it is
// coarse enough to be cheap and fine enough that the mid-bit sample point
// stays inside the bit even with a few percent of baud-rate mismatch.
`define UART_OVERSAMPLE  16

`endif

Assignments/Lab07-UART/rtl/uart_rx.v
`include "uart_pkg.vh"

module uart_rx #(
    parameter ODD_PARITY = 1'b0
) (
    input  wire                          Clk,
    input  wire                          RstN,
    input  wire                          os_tick,
    input  wire                          rxd,          

    output reg  [`UART_RX_REG_BITS-1:0]  rx_reg,      
    output wire [`UART_DATA_BITS-1:0]    rx_data,    
    output reg                           rx_valid,    
    output reg                           parity_err,
    output reg                           frame_err,
    output wire                          rx_busy
);
    localparam integer OS = `UART_OVERSAMPLE;

    localparam [2:0] IDLE  = 3'd0,
                     START = 3'd1,
                     RECV  = 3'd2,
                     STOP  = 3'd3,
                     RESYN = 3'd4;   

    reg  rx_s0, rx_s1;
    always @(posedge Clk or negedge RstN) begin
        if (!RstN) {rx_s0, rx_s1} <= 2'b11;
        else       {rx_s0, rx_s1} <= {rxd, rx_s0};
    end

    reg [2:0]                        st;
    reg [3:0]                        os;
    reg [2:0]                        nbit;
    reg [`UART_RX_REG_BITS-1:0]      sh;

    assign rx_data = rx_reg[`UART_DATA_BITS-1:0];
    assign rx_busy = (st != IDLE);

    wire exp_par = ODD_PARITY ? ~(^sh[`UART_DATA_BITS-1:0]) : (^sh[`UART_DATA_BITS-1:0]);

    always @(posedge Clk or negedge RstN) begin
        if (!RstN) begin
            st         <= IDLE;
            os         <= 4'd0;
            nbit       <= 3'd0;
            sh         <= {`UART_RX_REG_BITS{1'b0}};
            rx_reg     <= {`UART_RX_REG_BITS{1'b0}};
            rx_valid   <= 1'b0;
            parity_err <= 1'b0;
            frame_err  <= 1'b0;
        end else begin
            rx_valid <= 1'b0;

            case (st)
                IDLE: if (!rx_s1) begin      
                    os <= 4'd0;
                    st <= START;
                end

                START: if (os_tick) begin
                    if (os == OS/2 - 1) begin
                        if (rx_s1) begin
                            st <= IDLE;    
                        end else begin
                            os   <= 4'd0;
                            nbit <= 3'd0;
                            st   <= RECV;
                        end
                    end else begin
                        os <= os + 4'd1;
                    end
                end

                RECV: if (os_tick) begin
                    if (os == OS-1) begin
                        os   <= 4'd0;
                        sh   <= {sh[`UART_RX_REG_BITS-2:0], rx_s1};
                        nbit <= nbit + 3'd1;
                        if (nbit == `UART_RX_REG_BITS - 1) st <= STOP;
                    end else begin
                        os <= os + 4'd1;
                    end
                end

                STOP: if (os_tick) begin
                    if (os == OS-1) begin
                        os         <= 4'd0;
                        rx_reg     <= sh;
                        parity_err <= (sh[`UART_RX_REG_BITS-1] != exp_par);
                        frame_err  <= ~rx_s1;      
                        rx_valid   <= 1'b1;
                        st         <= rx_s1 ? IDLE : RESYN;
                    end else begin
                        os <= os + 4'd1;
                    end
                end

                RESYN: if (rx_s1) st <= IDLE;

                default: st <= IDLE;
            endcase
        end
    end
endmodule

Assignments/Lab07-UART/rtl/uart_tx.v
`include "uart_pkg.vh"

module uart_tx #(
    parameter ODD_PARITY = 1'b0
) (
    input  wire                        Clk,
    input  wire                        RstN,
    input  wire                        os_tick,     
    input  wire                        tx_start,   
    input  wire [`UART_DATA_BITS-1:0]  tx_data,   
    output reg                         txd,      
    output wire                        tx_busy,
    output reg                         tx_done   
);
    localparam [2:0] IDLE   = 3'd0,
                     START  = 3'd1,
                     PARITY = 3'd2,
                     DATA   = 3'd3,
                     STOP   = 3'd4;

    reg [2:0]                      st;
    reg [3:0]                      os;  
    reg [2:0]                      idx;  
    reg [`UART_DATA_BITS-1:0]      sh;  
    reg                            par;

    wire par_of_data = ODD_PARITY ? ~(^tx_data) : (^tx_data);

    wire bit_end = os_tick && (os == `UART_OVERSAMPLE - 1);

    assign tx_busy = (st != IDLE);

    always @(posedge Clk or negedge RstN) begin
        if (!RstN) begin
            st      <= IDLE;
            os      <= 4'd0;
            idx     <= 3'd0;
            sh      <= {`UART_DATA_BITS{1'b0}};
            par     <= 1'b0;
            txd     <= 1'b1;
            tx_done <= 1'b0;
        end else begin
            tx_done <= 1'b0;

            if (st != IDLE && os_tick)
                os <= bit_end ? 4'd0 : os + 4'd1;

            case (st)
                IDLE: begin
                    txd <= 1'b1;
                    if (tx_start) begin
                        sh  <= tx_data;
                        par <= par_of_data;
                        txd <= 1'b0;         
                        os  <= 4'd0;
                        idx <= `UART_DATA_BITS - 1;
                        st  <= START;
                    end
                end

                START: if (bit_end) begin
                    txd <= par;
                    st  <= PARITY;
                end

                PARITY: if (bit_end) begin
                    txd <= sh[`UART_DATA_BITS-1];
                    sh  <= {sh[`UART_DATA_BITS-2:0], 1'b0};
                    st  <= DATA;
                end

                DATA: if (bit_end) begin
                    if (idx == 3'd0) begin
                        txd <= 1'b1;         
                        st  <= STOP;
                    end else begin
                        txd <= sh[`UART_DATA_BITS-1];
                        sh  <= {sh[`UART_DATA_BITS-2:0], 1'b0};
                        idx <= idx - 3'd1;
                    end
                end

                STOP: if (bit_end) begin
                    txd     <= 1'b1;     
                    tx_done <= 1'b1;
                    st      <= IDLE;
                end

                default: st <= IDLE;
            endcase
        end
    end
endmodule

Assignments/Lab07-UART/rtl/baud_gen.v
module baud_gen #(
    parameter integer DIVISOR = 16
) (
    input  wire Clk,
    input  wire RstN,
    output wire tick
);
    reg [15:0] cnt;

    assign tick = (cnt == DIVISOR[15:0] - 16'd1);

    always @(posedge Clk or negedge RstN) begin
        if (!RstN)     cnt <= 16'd0;
        else if (tick) cnt <= 16'd0;
        else           cnt <= cnt + 16'd1;
    end
endmodule

Assignments/Lab07-UART/rtl/uart.v
`include "uart_pkg.vh"

module uart #(
    parameter integer OS_DIVISOR = 16,
    parameter         ODD_PARITY = 1'b0
) (
    input  wire                          Clk,
    input  wire                          RstN,

    input  wire                          tx_start,
    input  wire [`UART_DATA_BITS-1:0]    tx_data,
    output wire                          txd,
    output wire                          tx_busy,
    output wire                          tx_done,

    input  wire                          rxd,
    output wire [`UART_RX_REG_BITS-1:0]  rx_reg,     
    output wire [`UART_DATA_BITS-1:0]    rx_data,
    output wire                          rx_valid,
    output wire                          parity_err,
    output wire                          frame_err,
    output wire                          rx_busy,

    output wire                          os_tick 
);
    baud_gen #(.DIVISOR(OS_DIVISOR)) u_baud (
        .Clk(Clk), .RstN(RstN), .tick(os_tick)
    );

    uart_tx #(.ODD_PARITY(ODD_PARITY)) u_tx (
        .Clk      (Clk),
        .RstN     (RstN),
        .os_tick  (os_tick),
        .tx_start (tx_start),
        .tx_data  (tx_data),
        .txd      (txd),
        .tx_busy  (tx_busy),
        .tx_done  (tx_done)
    );

    uart_rx #(.ODD_PARITY(ODD_PARITY)) u_rx (
        .Clk        (Clk),
        .RstN       (RstN),
        .os_tick    (os_tick),
        .rxd        (rxd),
        .rx_reg     (rx_reg),
        .rx_data    (rx_data),
        .rx_valid   (rx_valid),
        .parity_err (parity_err),
        .frame_err  (frame_err),
        .rx_busy    (rx_busy)
    );
endmodule

Assignments/Lab07-UART/rtl/uart_link.v
`include "uart_pkg.vh"

module uart_link #(
    parameter integer A_OS_DIVISOR = 16,
    parameter integer B_OS_DIVISOR = 16,
    parameter         ODD_PARITY   = 1'b0
) (
    input  wire                          Clk,
    input  wire                          RstN,

    // unit A
    input  wire                          a_tx_start,
    input  wire [`UART_DATA_BITS-1:0]    a_tx_data,
    output wire                          a_tx_busy,
    output wire                          a_tx_done,
    output wire [`UART_RX_REG_BITS-1:0]  a_rx_reg,
    output wire [`UART_DATA_BITS-1:0]    a_rx_data,
    output wire                          a_rx_valid,
    output wire                          a_parity_err,
    output wire                          a_frame_err,

    // unit B
    input  wire                          b_tx_start,
    input  wire [`UART_DATA_BITS-1:0]    b_tx_data,
    output wire                          b_tx_busy,
    output wire                          b_tx_done,
    output wire [`UART_RX_REG_BITS-1:0]  b_rx_reg,
    output wire [`UART_DATA_BITS-1:0]    b_rx_data,
    output wire                          b_rx_valid,
    output wire                          b_parity_err,
    output wire                          b_frame_err,

    output wire                          a_to_b,
    output wire                          b_to_a
);
    uart #(.OS_DIVISOR(A_OS_DIVISOR), .ODD_PARITY(ODD_PARITY)) u_a (
        .Clk(Clk), .RstN(RstN),
        .tx_start(a_tx_start), .tx_data(a_tx_data),
        .txd(a_to_b), .tx_busy(a_tx_busy), .tx_done(a_tx_done),
        .rxd(b_to_a),
        .rx_reg(a_rx_reg), .rx_data(a_rx_data), .rx_valid(a_rx_valid),
        .parity_err(a_parity_err), .frame_err(a_frame_err),
        .rx_busy(), .os_tick()
    );

    uart #(.OS_DIVISOR(B_OS_DIVISOR), .ODD_PARITY(ODD_PARITY)) u_b (
        .Clk(Clk), .RstN(RstN),
        .tx_start(b_tx_start), .tx_data(b_tx_data),
        .txd(b_to_a), .tx_busy(b_tx_busy), .tx_done(b_tx_done),
        .rxd(a_to_b),
        .rx_reg(b_rx_reg), .rx_data(b_rx_data), .rx_valid(b_rx_valid),
        .parity_err(b_parity_err), .frame_err(b_frame_err),
        .rx_busy(), .os_tick()
    );
endmodule

Assignments/Lab07-UART/tb/tb_uart_wave.v
`timescale 1ns/1ps
`include "uart_pkg.vh"

`ifndef VCD_FILE
`define VCD_FILE "waves/uart.vcd"
`endif

module tb_uart_wave;
    localparam integer OSD = 2;    

    reg Clk = 1'b0, RstN = 1'b1;
    always #5 Clk = ~Clk;

    reg                       a_tx_start = 1'b0, b_tx_start = 1'b0;
    reg [`UART_DATA_BITS-1:0] a_tx_data  = 7'd0, b_tx_data  = 7'd0;

    wire [`UART_RX_REG_BITS-1:0] a_rx_reg, b_rx_reg;
    wire a_rx_valid, b_rx_valid, a_tx_busy, b_tx_busy;
    wire a_to_b, b_to_a;

    uart_link #(.A_OS_DIVISOR(OSD), .B_OS_DIVISOR(OSD)) link (
        .Clk(Clk), .RstN(RstN),
        .a_tx_start(a_tx_start), .a_tx_data(a_tx_data),
        .a_tx_busy(a_tx_busy), .a_tx_done(),
        .a_rx_reg(a_rx_reg), .a_rx_data(), .a_rx_valid(a_rx_valid),
        .a_parity_err(), .a_frame_err(),
        .b_tx_start(b_tx_start), .b_tx_data(b_tx_data),
        .b_tx_busy(b_tx_busy), .b_tx_done(),
        .b_rx_reg(b_rx_reg), .b_rx_data(), .b_rx_valid(b_rx_valid),
        .b_parity_err(), .b_frame_err(),
        .a_to_b(a_to_b), .b_to_a(b_to_a)
    );

    task automatic exchange;
        input [`UART_DATA_BITS-1:0] da;
        input [`UART_DATA_BITS-1:0] db;
        begin
            wait (!a_tx_busy && !b_tx_busy);
            @(negedge Clk); a_tx_data = da; b_tx_data = db;
                            a_tx_start = 1'b1; b_tx_start = 1'b1;
            @(negedge Clk); a_tx_start = 1'b0; b_tx_start = 1'b0;
            @(posedge a_rx_valid);
            @(posedge Clk);
        end
    endtask

    initial begin
        $dumpfile(`VCD_FILE);
        $dumpvars(0, tb_uart_wave);

        @(negedge Clk); RstN = 1'b0;
        repeat (4) @(negedge Clk); RstN = 1'b1;
        repeat (6) @(negedge Clk);

        exchange(7'h4B, 7'h7A);     
        repeat (20) @(negedge Clk);
        exchange(7'h4B, 7'h7A);

        repeat (60) @(negedge Clk);
        $display("Wrote VCD: %s", `VCD_FILE);
        $finish;
    end
endmodule

Assignments/Lab07-UART/waves/uart.vcd
$date
	Wed Aug 26 20:30:59 2026
$end
$version
	Icarus Verilog
$end
$timescale
	1ps
$end
$scope module tb_uart_wave $end
$var wire 1 ! b_tx_busy $end
$var wire 1 " b_to_a $end
$var wire 1 # b_rx_valid $end
$var wire 8 $ b_rx_reg [7:0] $end
$var wire 1 % a_tx_busy $end
$var wire 1 & a_to_b $end
$var wire 1 ' a_rx_valid $end
$var wire 8 ( a_rx_reg [7:0] $end
$var parameter 32 ) OSD $end
$var reg 1 * Clk $end
$var reg 1 + RstN $end
$var reg 7 , a_tx_data [6:0] $end
$var reg 1 - a_tx_start $end
$var reg 7 . b_tx_data [6:0] $end
$var reg 1 / b_tx_start $end
$scope module link $end
$var wire 1 * Clk $end
$var wire 1 + RstN $end
$var wire 7 0 a_tx_data [6:0] $end
$var wire 1 - a_tx_start $end
$var wire 7 1 b_tx_data [6:0] $end
$var wire 1 / b_tx_start $end
$var wire 1 2 b_tx_done $end
$var wire 1 ! b_tx_busy $end
$var wire 1 " b_to_a $end
$var wire 1 # b_rx_valid $end
$var wire 8 3 b_rx_reg [7:0] $end
$var wire 7 4 b_rx_data [6:0] $end
$var wire 1 5 b_parity_err $end
$var wire 1 6 b_frame_err $end
$var wire 1 7 a_tx_done $end
$var wire 1 % a_tx_busy $end
$var wire 1 & a_to_b $end
$var wire 1 ' a_rx_valid $end
$var wire 8 8 a_rx_reg [7:0] $end
$var wire 7 9 a_rx_data [6:0] $end
$var wire 1 : a_parity_err $end
$var wire 1 ; a_frame_err $end
$var parameter 32 < A_OS_DIVISOR $end
$var parameter 32 = B_OS_DIVISOR $end
$var parameter 1 > ODD_PARITY $end
$scope module u_a $end
$var wire 1 * Clk $end
$var wire 1 + RstN $end
$var wire 7 ? tx_data [6:0] $end
$var wire 1 - tx_start $end
$var wire 1 & txd $end
$var wire 1 7 tx_done $end
$var wire 1 % tx_busy $end
$var wire 1 " rxd $end
$var wire 1 ' rx_valid $end
$var wire 8 @ rx_reg [7:0] $end
$var wire 7 A rx_data [6:0] $end
$var wire 1 B rx_busy $end
$var wire 1 : parity_err $end
$var wire 1 C os_tick $end
$var wire 1 ; frame_err $end
$var parameter 1 D ODD_PARITY $end
$var parameter 32 E OS_DIVISOR $end
$scope module u_baud $end
$var wire 1 * Clk $end
$var wire 1 + RstN $end
$var wire 1 C tick $end
$var parameter 32 F DIVISOR $end
$var reg 16 G cnt [15:0] $end
$upscope $end
$scope module u_rx $end
$var wire 1 * Clk $end
$var wire 1 + RstN $end
$var wire 1 C os_tick $end
$var wire 1 " rxd $end
$var wire 7 H rx_data [6:0] $end
$var wire 1 B rx_busy $end
$var wire 1 I exp_par $end
$var parameter 3 J IDLE $end
$var parameter 1 K ODD_PARITY $end
$var parameter 32 L OS $end
$var parameter 3 M RECV $end
$var parameter 3 N RESYN $end
$var parameter 3 O START $end
$var parameter 3 P STOP $end
$var reg 1 ; frame_err $end
$var reg 3 Q nbit [2:0] $end
$var reg 4 R os [3:0] $end
$var reg 1 : parity_err $end
$var reg 8 S rx_reg [7:0] $end
$var reg 1 T rx_s0 $end
$var reg 1 U rx_s1 $end
$var reg 1 ' rx_valid $end
$var reg 8 V sh [7:0] $end
$var reg 3 W st [2:0] $end
$upscope $end
$scope module u_tx $end
$var wire 1 * Clk $end
$var wire 1 + RstN $end
$var wire 1 X bit_end $end
$var wire 1 C os_tick $end
$var wire 7 Y tx_data [6:0] $end
$var wire 1 - tx_start $end
$var wire 1 % tx_busy $end
$var wire 1 Z par_of_data $end
$var parameter 3 [ DATA $end
$var parameter 3 \ IDLE $end
$var parameter 1 ] ODD_PARITY $end
$var parameter 3 ^ PARITY $end
$var parameter 3 _ START $end
$var parameter 3 ` STOP $end
$var reg 3 a idx [2:0] $end
$var reg 4 b os [3:0] $end
$var reg 1 c par $end
$var reg 7 d sh [6:0] $end
$var reg 3 e st [2:0] $end
$var reg 1 7 tx_done $end
$var reg 1 & txd $end
$upscope $end
$upscope $end
$scope module u_b $end
$var wire 1 * Clk $end
$var wire 1 + RstN $end
$var wire 1 & rxd $end
$var wire 7 f tx_data [6:0] $end
$var wire 1 / tx_start $end
$var wire 1 " txd $end
$var wire 1 2 tx_done $end
$var wire 1 ! tx_busy $end
$var wire 1 # rx_valid $end
$var wire 8 g rx_reg [7:0] $end
$var wire 7 h rx_data [6:0] $end
$var wire 1 i rx_busy $end
$var wire 1 5 parity_err $end
$var wire 1 j os_tick $end
$var wire 1 6 frame_err $end
$var parameter 1 k ODD_PARITY $end
$var parameter 32 l OS_DIVISOR $end
$scope module u_baud $end
$var wire 1 * Clk $end
$var wire 1 + RstN $end
$var wire 1 j tick $end
$var parameter 32 m DIVISOR $end
$var reg 16 n cnt [15:0] $end
$upscope $end
$scope module u_rx $end
$var wire 1 * Clk $end
$var wire 1 + RstN $end
$var wire 1 j os_tick $end
$var wire 1 & rxd $end
$var wire 7 o rx_data [6:0] $end
$var wire 1 i rx_busy $end
$var wire 1 p exp_par $end
$var parameter 3 q IDLE $end
$var parameter 1 r ODD_PARITY $end
$var parameter 32 s OS $end
$var parameter 3 t RECV $end
$var parameter 3 u RESYN $end
$var parameter 3 v START $end
$var parameter 3 w STOP $end
$var reg 1 6 frame_err $end
$var reg 3 x nbit [2:0] $end
$var reg 4 y os [3:0] $end
$var reg 1 5 parity_err $end
$var reg 8 z rx_reg [7:0] $end
$var reg 1 { rx_s0 $end
$var reg 1 | rx_s1 $end
$var reg 1 # rx_valid $end
$var reg 8 } sh [7:0] $end
$var reg 3 ~ st [2:0] $end
$upscope $end
$scope module u_tx $end
$var wire 1 * Clk $end
$var wire 1 + RstN $end
$var wire 1 !" bit_end $end
$var wire 1 j os_tick $end
$var wire 7 "" tx_data [6:0] $end
$var wire 1 / tx_start $end
$var wire 1 ! tx_busy $end
$var wire 1 #" par_of_data $end
$var parameter 3 $" DATA $end
$var parameter 3 %" IDLE $end
$var parameter 1 &" ODD_PARITY $end
$var parameter 3 '" PARITY $end
$var parameter 3 (" START $end
$var parameter 3 )" STOP $end
$var reg 3 *" idx [2:0] $end
$var reg 4 +" os [3:0] $end
$var reg 1 ," par $end
$var reg 7 -" sh [6:0] $end
$var reg 3 ." st [2:0] $end
$var reg 1 2 tx_done $end
$var reg 1 " txd $end
$upscope $end
$upscope $end
$upscope $end
$scope task exchange $end
$upscope $end
$upscope $end
$enddefinitions $end
$comment Show the parameter values. $end
$dumpall
b100 )"
b1 ("
b10 '"
0&"
b0 %"
b11 $"
b11 w
b1 v
b100 u
b10 t
b10000 s
0r
b0 q
b10 m
b10 l
0k
b100 `
b1 _
b10 ^
0]
b0 \
b11 [
b11 P
b1 O
b100 N
b10 M
b10000 L
0K
b0 J
b10 F
b10 E
0D
0>
b10 =
b10 <
b10 )
$end
#0
$dumpvars
bx ."
bx -"
x,"
bx +"
bx *"
0#"
b0 ""
x!"
bx ~
bx }
x|
x{
bx z
bx y
bx x
xp
bx o
bx n
xj
xi
bx h
bx g
b0 f
bx e
bx d
xc
bx b
bx a
0Z
b0 Y
xX
bx W
bx V
xU
xT
bx S
bx R
bx Q
xI
bx H
bx G
xC
xB
bx A
bx @
b0 ?
x;
x:
bx 9
bx 8
x7
x6
x5
bx 4
bx 3
x2
b0 1
b0 0
0/
b0 .
0-
b0 ,
1+
0*
bx (
x'
x&
x%
bx $
x#
x"
x!
$end
#5000
0%
b0 e
07
0B
b0 W
0'
0!
b0 ."
02
0i
b0 ~
0#
1*
#10000
b0 4
b0 h
b0 o
0p
0!"
b0 9
b0 A
b0 H
0I
0X
06
05
b0 $
b0 3
b0 g
b0 z
b0 }
b0 x
b0 y
1{
1|
1"
0,"
b0 -"
b0 *"
b0 +"
0j
b0 n
0;
0:
b0 (
b0 8
b0 @
b0 S
b0 V
b0 Q
b0 R
1T
1U
1&
0c
b0 d
b0 a
b0 b
0C
b0 G
0+
0*
#15000
1*
#20000
0*
#25000
1*
#30000
0*
#35000
1*
#40000
0*
#45000
1*
#50000
1+
0*
#55000
1C
b1 G
1j
b1 n
1*
#60000
0*
#65000
0j
b0 n
0C
b0 G
1*
#70000
0*
#75000
1C
b1 G
1j
b1 n
1*
#80000
0*
#85000
0j
b0 n
0C
b0 G
1*
#90000
0*
#95000
1C
b1 G
1j
b1 n
1*
#100000
0*
#105000
0j
b0 n
0C
b0 G
1*
#110000
0*
#115000
1C
b1 G
1j
b1 n
1*
#120000
1/
1-
1#"
b1111010 .
b1111010 1
b1111010 f
b1111010 ""
b1001011 ,
b1001011 0
b1001011 ?
b1001011 Y
0*
#125000
1!
b1 ."
b110 *"
0"
1,"
b1111010 -"
0j
b0 n
1%
b1 e
b110 a
0&
b1001011 d
0C
b0 G
1*
#130000
0/
0-
0*
#135000
1C
b1 G
0T
1j
b1 n
0{
1*
#140000
0*
#145000
0|
b1 +"
0j
b0 n
0U
b1 b
0C
b0 G
1*
#150000
0*
#155000
1C
b1 G
1B
b1 W
1j
b1 n
1i
b1 ~
1*
#160000
0*
#165000
b1 y
b10 +"
0j
b0 n
b1 R
b10 b
0C
b0 G
1*
#170000
0*
#175000
1C
b1 G
1j
b1 n
1*
#180000
0*
#185000
b10 y
b11 +"
0j
b0 n
b10 R
b11 b
0C
b0 G
1*
#190000
0*
#195000
1C
b1 G
1j
b1 n
1*
#200000
0*
#205000
b11 y
b100 +"
0j
b0 n
b11 R
b100 b
0C
b0 G
1*
#210000
0*
#215000
1C
b1 G
1j
b1 n
1*
#220000
0*
#225000
b100 y
b101 +"
0j
b0 n
b100 R
b101 b
0C
b0 G
1*
#230000
0*
#235000
1C
b1 G
1j
b1 n
1*
#240000
0*
#245000
b101 y
b110 +"
0j
b0 n
b101 R
b110 b
0C
b0 G
1*
#250000
0*
#255000
1C
b1 G
1j
b1 n
1*
#260000
0*
#265000
b110 y
b111 +"
0j
b0 n
b110 R
b111 b
0C
b0 G
1*
#270000
0*
#275000
1C
b1 G
1j
b1 n
1*
#280000
0*
#285000
b111 y
b1000 +"
0j
b0 n
b111 R
b1000 b
0C
b0 G
1*
#290000
0*
#295000
1C
b1 G
1j
b1 n
1*
#300000
0*
#305000
b10 ~
b0 y
b1001 +"
0j
b0 n
b10 W
b0 R
b1001 b
0C
b0 G
1*
#310000
0*
#315000
1C
b1 G
1j
b1 n
1*
#320000
0*
#325000
b1 y
b1010 +"
0j
b0 n
b1 R
b1010 b
0C
b0 G
1*
#330000
0*
#335000
1C
b1 G
1j
b1 n
1*
#340000
0*
#345000
b10 y
b1011 +"
0j
b0 n
b10 R
b1011 b
0C
b0 G
1*
#350000
0*
#355000
1C
b1 G
1j
b1 n
1*
#360000
0*
#365000
b11 y
b1100 +"
0j
b0 n
b11 R
b1100 b
0C
b0 G
1*
#370000
0*
#375000
1C
b1 G
1j
b1 n
1*
#380000
0*
#385000
b100 y
b1101 +"
0j
b0 n
b100 R
b1101 b
0C
b0 G
1*
#390000
0*
#395000
1C
b1 G
1j
b1 n
1*
#400000
0*
#405000
b101 y
b1110 +"
0j
b0 n
b101 R
b1110 b
0C
b0 G
1*
#410000
0*
#415000
1C
b1 G
1j
b1 n
1*
#420000
0*
#425000
b110 y
b1111 +"
0j
b0 n
b110 R
b1111 b
0C
b0 G
1*
#430000
0*
#435000
1X
1!"
1C
b1 G
1j
b1 n
1*
#440000
0*
#445000
0!"
0X
b111 y
b10 ."
1"
b0 +"
0j
b0 n
b111 R
b10 e
b0 b
0C
b0 G
1*
#450000
0*
#455000
1C
b1 G
1T
1j
b1 n
1*
#460000
0*
#465000
b1000 y
b1 +"
0j
b0 n
b1000 R
1U
b1 b
0C
b0 G
1*
#470000
0*
#475000
1C
b1 G
1j
b1 n
1*
#480000
0*
#485000
b1001 y
b10 +"
0j
b0 n
b1001 R
b10 b
0C
b0 G
1*
#490000
0*
#495000
1C
b1 G
1j
b1 n
1*
#500000
0*
#505000
b1010 y
b11 +"
0j
b0 n
b1010 R
b11 b
0C
b0 G
1*
#510000
0*
#515000
1C
b1 G
1j
b1 n
1*
#520000
0*
#525000
b1011 y
b100 +"
0j
b0 n
b1011 R
b100 b
0C
b0 G
1*
#530000
0*
#535000
1C
b1 G
1j
b1 n
1*
#540000
0*
#545000
b1100 y
b101 +"
0j
b0 n
b1100 R
b101 b
0C
b0 G
1*
#550000
0*
#555000
1C
b1 G
1j
b1 n
1*
#560000
0*
#565000
b1101 y
b110 +"
0j
b0 n
b1101 R
b110 b
0C
b0 G
1*
#570000
0*
#575000
1C
b1 G
1j
b1 n
1*
#580000
0*
#585000
b1110 y
b111 +"
0j
b0 n
b1110 R
b111 b
0C
b0 G
1*
#590000
0*
#595000
1C
b1 G
1j
b1 n
1*
#600000
0*
#605000
b1111 y
b1000 +"
0j
b0 n
b1111 R
b1000 b
0C
b0 G
1*
#610000
0*
#615000
1C
b1 G
1j
b1 n
1*
#620000
0*
#625000
1I
b1 x
b0 y
b1001 +"
0j
b0 n
b1 Q
b1 V
b0 R
b1001 b
0C
b0 G
1*
#630000
0*
#635000
1C
b1 G
1j
b1 n
1*
#640000
0*
#645000
b1 y
b1010 +"
0j
b0 n
b1 R
b1010 b
0C
b0 G
1*
#650000
0*
#655000
1C
b1 G
1j
b1 n
1*
#660000
0*
#665000
b10 y
b1011 +"
0j
b0 n
b10 R
b1011 b
0C
b0 G
1*
#670000
0*
#675000
1C
b1 G
1j
b1 n
1*
#680000
0*
#685000
b11 y
b1100 +"
0j
b0 n
b11 R
b1100 b
0C
b0 G
1*
#690000
0*
#695000
1C
b1 G
1j
b1 n
1*
#700000
0*
#705000
b100 y
b1101 +"
0j
b0 n
b100 R
b1101 b
0C
b0 G
1*
#710000
0*
#715000
1C
b1 G
1j
b1 n
1*
#720000
0*
#725000
b101 y
b1110 +"
0j
b0 n
b101 R
b1110 b
0C
b0 G
1*
#730000
0*
#735000
1C
b1 G
1j
b1 n
1*
#740000
0*
#745000
b110 y
b1111 +"
0j
b0 n
b110 R
b1111 b
0C
b0 G
1*
#750000
0*
#755000
1X
1!"
1C
b1 G
1j
b1 n
1*
#760000
0*
#765000
0!"
0X
b111 y
b11 ."
b1110100 -"
b0 +"
0j
b0 n
b111 R
b11 e
b10110 d
1&
b0 b
0C
b0 G
1*
#770000
0*
#775000
1C
b1 G
1j
b1 n
1{
1*
#780000
0*
#785000
b1000 y
1|
b1 +"
0j
b0 n
b1000 R
b1 b
0C
b0 G
1*
#790000
0*
#795000
1C
b1 G
1j
b1 n
1*
#800000
0*
#805000
b1001 y
b10 +"
0j
b0 n
b1001 R
b10 b
0C
b0 G
1*
#810000
0*
#815000
1C
b1 G
1j
b1 n
1*
#820000
0*
#825000
b1010 y
b11 +"
0j
b0 n
b1010 R
b11 b
0C
b0 G
1*
#830000
0*
#835000
1C
b1 G
1j
b1 n
1*
#840000
0*
#845000
b1011 y
b100 +"
0j
b0 n
b1011 R
b100 b
0C
b0 G
1*
#850000
0*
#855000
1C
b1 G
1j
b1 n
1*
#860000
0*
#865000
b1100 y
b101 +"
0j
b0 n
b1100 R
b101 b
0C
b0 G
1*
#870000
0*
#875000
1C
b1 G
1j
b1 n
1*
#880000
0*
#885000
b1101 y
b110 +"
0j
b0 n
b1101 R
b110 b
0C
b0 G
1*
#890000
0*
#895000
1C
b1 G
1j
b1 n
1*
#900000
0*
#905000
b1110 y
b111 +"
0j
b0 n
b1110 R
b111 b
0C
b0 G
1*
#910000
0*
#915000
1C
b1 G
1j
b1 n
1*
#920000
0*
#925000
b1111 y
b1000 +"
0j
b0 n
b1111 R
b1000 b
0C
b0 G
1*
#930000
0*
#935000
1C
b1 G
1j
b1 n
1*
#940000
0*
#945000
1p
0I
b10 x
b1 }
b0 y
b1001 +"
0j
b0 n
b10 Q
b11 V
b0 R
b1001 b
0C
b0 G
1*
#950000
0*
#955000
1C
b1 G
1j
b1 n
1*
#960000
0*
#965000
b1 y
b1010 +"
0j
b0 n
b1 R
b1010 b
0C
b0 G
1*
#970000
0*
#975000
1C
b1 G
1j
b1 n
1*
#980000
0*
#985000
b10 y
b1011 +"
0j
b0 n
b10 R
b1011 b
0C
b0 G
1*
#990000
0*
#995000
1C
b1 G
1j
b1 n
1*
#1000000
0*
#1005000
b11 y
b1100 +"
0j
b0 n
b11 R
b1100 b
0C
b0 G
1*
#1010000
0*
#1015000
1C
b1 G
1j
b1 n
1*
#1020000
0*
#1025000
b100 y
b1101 +"
0j
b0 n
b100 R
b1101 b
0C
b0 G
1*
#1030000
0*
#1035000
1C
b1 G
1j
b1 n
1*
#1040000
0*
#1045000
b101 y
b1110 +"
0j
b0 n
b101 R
b1110 b
0C
b0 G
1*
#1050000
0*
#1055000
1C
b1 G
1j
b1 n
1*
#1060000
0*
#1065000
b110 y
b1111 +"
0j
b0 n
b110 R
b1111 b
0C
b0 G
1*
#1070000
0*
#1075000
1X
1!"
1C
b1 G
1j
b1 n
1*
#1080000
0*
#1085000
0!"
0X
b111 y
b101 *"
b1101000 -"
b0 +"
0j
b0 n
b111 R
b101 a
b101100 d
0&
b0 b
0C
b0 G
1*
#1090000
0*
#1095000
1C
b1 G
1j
b1 n
0{
1*
#1100000
0*
#1105000
b1000 y
0|
b1 +"
0j
b0 n
b1000 R
b1 b
0C
b0 G
1*
#1110000
0*
#1115000
1C
b1 G
1j
b1 n
1*
