Assignments/Lab04-Behavioral-Stack/rtl/stack.v
module stack #(
    parameter integer WIDTH = 4,
    parameter integer DEPTH = 8
) (
    input  wire                  Clk,
    input  wire                  RstN,
    input  wire [WIDTH-1:0]      Data_In,
    input  wire                  Push,
    input  wire                  Pop,
    output reg  [WIDTH-1:0]      Data_Out,
    output wire                  Full,
    output wire                  Empty
);
    localparam integer PTR_W = $clog2(DEPTH) + 1;

    reg [WIDTH-1:0] mem [0:DEPTH-1];
    reg [PTR_W-1:0] sp;                 

    integer i;

    assign Empty = (sp == 0);
    assign Full  = (sp == DEPTH[PTR_W-1:0]);

    wire do_push = Push & ~Pop & ~Full;
    wire do_pop  = Pop  & ~Push & ~Empty;

    always @(posedge Clk or negedge RstN) begin
        if (!RstN) begin
            sp <= {PTR_W{1'b0}};
            for (i = 0; i < DEPTH; i = i + 1)
                mem[i] <= {WIDTH{1'b0}};
        end else begin
            if (do_push) begin
                mem[sp] <= Data_In;
                sp      <= sp + 1'b1;
            end else if (do_pop) begin
                sp <= sp - 1'b1;
            end
        end
    end

    always @(*) begin
        if (sp == 0)
            Data_Out = {WIDTH{1'b0}};
        else
            Data_Out = mem[sp - 1'b1];
    end
endmodule

Assignments/Lab04-Behavioral-Stack/tb/tb_stack_wave.v
`timescale 1ns/1ps

// Short, presentation-friendly stack demo that dumps a VCD.
// Scenario is chosen so every interesting event is visible in one picture:
// reset -> pop-when-empty (ignored) -> fill to Full -> push-when-full
// (ignored) -> drain to Empty -> pop-when-empty (ignored).
`ifndef VCD_FILE
`define VCD_FILE "waves/stack.vcd"
`endif

module tb_stack_wave;
    localparam integer WIDTH = 4;
    localparam integer DEPTH = 8;

    reg                  Clk, RstN, Push, Pop;
    reg  [WIDTH-1:0]     Data_In;
    wire [WIDTH-1:0]     Data_Out;
    wire                 Full, Empty;

    stack #(.WIDTH(WIDTH), .DEPTH(DEPTH)) dut (
        .Clk(Clk), .RstN(RstN), .Data_In(Data_In),
        .Push(Push), .Pop(Pop),
        .Data_Out(Data_Out), .Full(Full), .Empty(Empty)
    );

    initial Clk = 1'b0;
    always #5 Clk = ~Clk;

    integer k;

    task automatic step;
        input             p_push;
        input             p_pop;
        input [WIDTH-1:0] p_din;
        begin
            @(negedge Clk);
            Push = p_push; Pop = p_pop; Data_In = p_din;
            @(posedge Clk);
        end
    endtask

    initial begin
        $dumpfile(`VCD_FILE);
        $dumpvars(0, tb_stack_wave);

        RstN = 1'b1; Push = 0; Pop = 0; Data_In = 0;

        // reset
        @(negedge Clk); RstN = 1'b0;
        @(negedge Clk); RstN = 1'b1;

        step(1'b0, 1'b1, 4'h0);            // pop on empty -> ignored
        for (k = 1; k <= DEPTH; k = k + 1) // fill: 1..8, Full rises at 8
            step(1'b1, 1'b0, k[WIDTH-1:0]);
        step(1'b1, 1'b0, 4'hF);            // push on full -> ignored
        for (k = 0; k < DEPTH; k = k + 1)  // drain: 8..1, Empty rises at end
            step(1'b0, 1'b1, 4'h0);
        step(1'b0, 1'b1, 4'h0);            // pop on empty -> ignored
        step(1'b0, 1'b0, 4'h0);            // idle

        @(negedge Clk);
        Push = 0; Pop = 0;
        #10;
        $display("Wrote VCD: %s", `VCD_FILE);
        $finish;
    end
endmodule

Assignments/Lab04-Behavioral-Stack/waves/stack.vcd
$date
	Sat Aug 22 14:06:15 2026
$end
$version
	Icarus Verilog
$end
$timescale
	1ps
$end
$scope module tb_stack_wave $end
$var wire 1 ! Full $end
$var wire 1 " Empty $end
$var wire 4 # Data_Out [3:0] $end
$var parameter 32 $ DEPTH $end
$var parameter 32 % WIDTH $end
$var reg 1 & Clk $end
$var reg 4 ' Data_In [3:0] $end
$var reg 1 ( Pop $end
$var reg 1 ) Push $end
$var reg 1 * RstN $end
$var integer 32 + k [31:0] $end
$scope module dut $end
$var wire 1 & Clk $end
$var wire 4 , Data_In [3:0] $end
$var wire 1 ( Pop $end
$var wire 1 ) Push $end
$var wire 1 * RstN $end
$var wire 1 - do_pop $end
$var wire 1 . do_push $end
$var wire 1 ! Full $end
$var wire 1 " Empty $end
$var parameter 32 / DEPTH $end
$var parameter 32 0 PTR_W $end
$var parameter 32 1 WIDTH $end
$var reg 4 2 Data_Out [3:0] $end
$var reg 4 3 sp [3:0] $end
$var integer 32 4 i [31:0] $end
$upscope $end
$scope task step $end
$upscope $end
$upscope $end
$enddefinitions $end
$comment Show the parameter values. $end
$dumpall
b100 1
b100 0
b1000 /
b100 %
b1000 $
$end
#0
$dumpvars
bx 4
bx 3
bx 2
0.
0-
b0 ,
bx +
1*
0)
0(
b0 '
0&
bx #
x"
x!
$end
#5000
1&
#10000
b0 #
b0 2
1"
0!
b0 3
b1000 4
0*
0&
#15000
b1000 4
1&
#20000
1*
0&
#25000
1&
#30000
1(
0&
#35000
b1 +
1&
#40000
1.
b1 '
b1 ,
0(
1)
0&
#45000
b1 #
b1 2
0"
b1 3
b10 +
1&
#50000
b10 '
b10 ,
0&
#55000
b10 #
b10 2
b10 3
b11 +
1&
#60000
b11 '
b11 ,
0&
#65000
b11 #
b11 2
b11 3
b100 +
1&
#70000
b100 '
b100 ,
0&
#75000
b100 #
b100 2
b100 3
b101 +
1&
#80000
b101 '
b101 ,
0&
#85000
b101 #
b101 2
b101 3
b110 +
1&
#90000
b110 '
b110 ,
0&
#95000
b110 #
b110 2
b110 3
b111 +
1&
#100000
b111 '
b111 ,
0&
#105000
b111 #
b111 2
b111 3
b1000 +
1&
#110000
b1000 '
b1000 ,
0&
#115000
0.
b1000 #
b1000 2
1!
b1000 3
b1001 +
1&
#120000
b1111 '
b1111 ,
0&
#125000
b0 +
1&
#130000
1-
b0 '
b0 ,
1(
0)
0&
#135000
b111 #
b111 2
0!
b111 3
b1 +
1&
#140000
0&
#145000
b110 #
b110 2
b110 3
b10 +
1&
#150000
0&
#155000
b101 #
b101 2
b101 3
b11 +
1&
#160000
0&
#165000
b100 #
b100 2
b100 3
b100 +
1&
#170000
0&
#175000
b11 #
b11 2
b11 3
b101 +
1&
#180000
0&
#185000
b10 #
b10 2
b10 3
b110 +
1&
#190000
0&
#195000
b1 #
b1 2
b1 3
b111 +
1&
#200000
0&
#205000
0-
b0 #
b0 2
1"
b0 3
b1000 +
1&
#210000
0&
#215000
1&
#220000
0(
0&
