Assignments/Lab08-Complex-ALU/rtl/complex_pkg.vh
// Shared definitions for the complex-number machine.
//
// Number representation
// --------------------
// A complex value is a pair of 8-bit SIGNED two's-complement components packed
// into one 16-bit word:
//
//     word = { imag[7:0], real[7:0] }        range of each part: -128 .. +127
//
// Results are SATURATED, not wrapped: a component that leaves the range is
// clamped to -128 or +127 and a flag is raised. For a machine whose whole job
// is arithmetic on measured quantities this is the useful behaviour -- a value
// that is too large should read as "very large", not silently change sign.
//
// Instruction word (32 bits, one memory word)
// -------------------------------------------
//     [31:28] opcode
//     [27:25] rd
//     [24:22] rs
//     [21:19] rt
//     [18:16] unused
//     [15:0]  immediate, itself a complex word { imag, real }
`ifndef COMPLEX_PKG_VH
`define COMPLEX_PKG_VH

`define CX_HALF   8      // bits per component
`define CX_WORD   16     // bits per complex value
`define CX_WIDE   17     // adder width: two 16-bit products still fit
`define IW        32     // instruction width
`define MEM_WORDS 32     // "a 32-word memory"
`define MEM_AW    5
`define REG_AW    3      // 8 complex registers

// --- opcodes ---
`define OP_NOP   4'h0
`define OP_LDI   4'h1    // rd <- imm
`define OP_MOV   4'h2    // rd <- rs
`define OP_ADD   4'h3    // rd <- rs + rt
`define OP_SUB   4'h4    // rd <- rs - rt
`define OP_MUL   4'h5    // rd <- rs * rt
`define OP_HALT  4'hF

// --- what the shared ALU is asked to do ---
`define ALU_ADD  2'd0
`define ALU_SUB  2'd1
`define ALU_MUL  2'd2

`endif

Assignments/Lab08-Complex-ALU/rtl/add_unit.v
// THE adder/subtractor of the machine, instantiated exactly once.
//
// Width is 17 bits because the same unit has to serve two very different
// jobs: adding two 8-bit components (9 bits would do) and combining two
// 16-bit partial products of a complex multiply (17 bits needed).
//
// Subtraction is not a second unit: x - y is the same adder with y inverted
// and a carry into the low bit, which is how a synthesiser implements it.
module add_unit (
    input  wire signed [16:0] x,
    input  wire signed [16:0] y,
    input  wire               sub,
    output wire signed [16:0] s
);
    assign s = sub ? (x - y) : (x + y);
endmodule

Assignments/Lab08-Complex-ALU/rtl/mul_unit.v
// THE multiplier of the machine.
//
// The lab sheet allows a single adder and a single multiplier in the whole
// design, so this module is instantiated exactly once -- inside complex_alu --
// and every product the machine ever computes passes through it, one per
// clock cycle.
module mul_unit (
    input  wire signed [7:0]  x,
    input  wire signed [7:0]  y,
    output wire signed [15:0] p
);
    assign p = x * y;
endmodule

Assignments/Lab08-Complex-ALU/rtl/complex_alu.v
`include "complex_pkg.vh"

module complex_alu (
    input  wire                    Clk,
    input  wire                    RstN,
    input  wire                    start,
    input  wire [1:0]              op,      // ALU_ADD / ALU_SUB / ALU_MUL
    input  wire [`CX_WORD-1:0]     a,       // { imag, real }
    input  wire [`CX_WORD-1:0]     b,
    output reg  [`CX_WORD-1:0]     y,
    output reg                     ovf,     // a component had to be clamped
    output wire                    busy,
    output reg                     done     // 1 clk pulse, y valid in that cycle
);
    localparam [2:0] IDLE = 3'd0,
                     A_RE = 3'd1, A_IM = 3'd2,
                     M1   = 3'd3, M2   = 3'd4, M3 = 3'd5, M4 = 3'd6;

    reg [2:0]                st;
    reg [`CX_WORD-1:0]       a_r, b_r;      // operands latched at start
    reg [1:0]                op_r;
    reg signed [15:0]        t1, t3;        // latched partial products
    reg                      sat_r;         // real part had to be clamped

    wire signed [7:0] ar = a_r[7:0],  ai = a_r[15:8];
    wire signed [7:0] br = b_r[7:0],  bi = b_r[15:8];

    // ---- the one multiplier and the one adder ----
    reg  signed [7:0]  mx, my;
    wire signed [15:0] mp;
    mul_unit u_mul (.x(mx), .y(my), .p(mp));

    reg  signed [16:0] ax, ay;
    reg                asub;
    wire signed [16:0] as;
    add_unit u_add (.x(ax), .y(ay), .sub(asub), .s(as));

    assign busy = (st != IDLE);

    // Clamp a 17-bit result into a signed 8-bit component.
    function signed [7:0] sat8;
        input signed [16:0] v;
        begin
            if      (v >  17'sd127) sat8 =  8'sd127;
            else if (v < -17'sd128) sat8 = -8'sd128;
            else                    sat8 =  v[7:0];
        end
    endfunction

    function clipped;
        input signed [16:0] v;
        begin
            clipped = (v > 17'sd127) || (v < -17'sd128);
        end
    endfunction

    // ---- operand routing: which numbers reach the two shared units ----
    always @(*) begin
        mx   = 8'sd0;
        my   = 8'sd0;
        ax   = 17'sd0;
        ay   = 17'sd0;
        asub = 1'b0;
        case (st)
            A_RE: begin
                ax   = {{9{ar[7]}}, ar};
                ay   = {{9{br[7]}}, br};
                asub = (op_r == `ALU_SUB);
            end
            A_IM: begin
                ax   = {{9{ai[7]}}, ai};
                ay   = {{9{bi[7]}}, bi};
                asub = (op_r == `ALU_SUB);
            end
            M1: begin mx = ar; my = br; end
            M2: begin
                mx   = ai;  my = bi;              // computing ai*bi ...
                ax   = {t1[15], t1};              // ... while the adder does
                ay   = {mp[15], mp};              //     ar*br - ai*bi
                asub = 1'b1;
            end
            M3: begin mx = ar; my = bi; end
            M4: begin
                mx   = ai;  my = br;              // computing ai*br ...
                ax   = {t3[15], t3};              // ... while the adder does
                ay   = {mp[15], mp};              //     ar*bi + ai*br
                asub = 1'b0;
            end
            default: ;
        endcase
    end

    always @(posedge Clk or negedge RstN) begin
        if (!RstN) begin
            st    <= IDLE;
            y     <= {`CX_WORD{1'b0}};
            ovf   <= 1'b0;
            done  <= 1'b0;
            a_r   <= {`CX_WORD{1'b0}};
            b_r   <= {`CX_WORD{1'b0}};
            op_r  <= 2'd0;
            t1    <= 16'sd0;
            t3    <= 16'sd0;
            sat_r <= 1'b0;
        end else begin
            done <= 1'b0;
            case (st)
                IDLE: if (start) begin
                    a_r   <= a;
                    b_r   <= b;
                    op_r  <= op;
                    sat_r <= 1'b0;
                    st    <= (op == `ALU_MUL) ? M1 : A_RE;
                end

                A_RE: begin
                    y[7:0] <= sat8(as);
                    sat_r  <= clipped(as);
                    st     <= A_IM;
                end
                A_IM: begin
                    y[15:8] <= sat8(as);
                    ovf     <= sat_r | clipped(as);
                    done    <= 1'b1;
                    st      <= IDLE;
                end

                M1: begin t1 <= mp; st <= M2; end
                M2: begin
                    y[7:0] <= sat8(as);
                    sat_r  <= clipped(as);
                    st     <= M3;
                end
                M3: begin t3 <= mp; st <= M4; end
                M4: begin
                    y[15:8] <= sat8(as);
                    ovf     <= sat_r | clipped(as);
                    done    <= 1'b1;
                    st      <= IDLE;
                end

                default: st <= IDLE;
            endcase
        end
    end
endmodule

Assignments/Lab08-Complex-ALU/rtl/regfile.v
`include "complex_pkg.vh"

module regfile (
    input  wire                    Clk,
    input  wire                    RstN,

    input  wire                    we,
    input  wire [`REG_AW-1:0]      wa,
    input  wire [`CX_WORD-1:0]     wd,

    input  wire [`REG_AW-1:0]      ra1,
    input  wire [`REG_AW-1:0]      ra2,
    output wire [`CX_WORD-1:0]     rd1,
    output wire [`CX_WORD-1:0]     rd2,

    input  wire [`REG_AW-1:0]      ra_dbg,
    output wire [`CX_WORD-1:0]     rd_dbg
);
    localparam integer NREG = (1 << `REG_AW);

    reg [`CX_WORD-1:0] r [0:NREG-1];
    integer i;

    always @(posedge Clk or negedge RstN) begin
        if (!RstN) for (i = 0; i < NREG; i = i + 1) r[i] <= {`CX_WORD{1'b0}};
        else if (we) r[wa] <= wd;
    end

    assign rd1    = r[ra1];
    assign rd2    = r[ra2];
    assign rd_dbg = r[ra_dbg];
endmodule

Assignments/Lab08-Complex-ALU/rtl/imem.v
`include "complex_pkg.vh"

// The 32-word memory the lab sheet specifies, holding the program.
//
// The write port is how a program gets in: on a board it would be driven by a
// small loader (or replaced by a ROM initialised at synthesis time); in the
// testbenches it is driven directly while the pipeline is held with run = 0.
// Reading is combinational so the fetch stage can register the instruction on
// the same edge it advances the program counter.
//
// The program counter is 5 bits and simply wraps from word 31 back to word 0,
// so a program with no HALT in it runs for ever rather than falling off the
// end. Every program in the testbenches fills unused words with HALT, which is
// the sane convention for a memory this small.
module imem (
    input  wire                    Clk,
    input  wire                    we,
    input  wire [`MEM_AW-1:0]      waddr,
    input  wire [`IW-1:0]          wdata,
    input  wire [`MEM_AW-1:0]      raddr,
    output wire [`IW-1:0]          rdata
);
    reg [`IW-1:0] mem [0:`MEM_WORDS-1];

    always @(posedge Clk) if (we) mem[waddr] <= wdata;

    assign rdata = mem[raddr];
endmodule

Assignments/Lab08-Complex-ALU/rtl/complex_cpu.v
`include "complex_pkg.vh"

// Part (c) of the lab: the machine that reads instructions out of the 32-word
// memory and executes them in a pipeline.
//
// Stages
// ------
//   IF   read imem at PC, register the instruction
//   ID   decode, read the register file, resolve hazards
//   EX   the shared complex ALU -- 2 or 4 cycles of work, or one cycle for the
//        instructions that need no arithmetic at all (LDI / MOV / NOP)
//   WB   write the result back
//
// The interesting consequence of the single-adder / single-multiplier rule is
// that EX cannot itself be pipelined: there is one multiplier, so only one
// product can be in flight at a time. IF, ID and WB still overlap with EX --
// while a multiply is grinding away, the next instruction is already fetched
// and decoded and the previous result is being written back -- but EX is the
// throughput limit by construction, not by accident.
//
// Two interlocks keep that correct:
//   * EX accepts a new instruction only when it is free (or freeing this
//     cycle), so a long operation stalls decode and fetch behind it;
//   * an instruction whose source register is still being produced in EX waits
//     in ID. Once the producer reaches WB the value is forwarded straight into
//     the decode stage, so the wait is exactly as long as it has to be.
module complex_cpu (
    input  wire                    Clk,
    input  wire                    RstN,
    input  wire                    run,        // 0 = hold (used while loading)

    // program load port
    input  wire                    prog_we,
    input  wire [`MEM_AW-1:0]      prog_addr,
    input  wire [`IW-1:0]          prog_data,

    // observation
    input  wire [`REG_AW-1:0]      dbg_raddr,
    output wire [`CX_WORD-1:0]     dbg_rdata,
    output reg  [`MEM_AW-1:0]      pc,
    output reg                     halted,      // fetching has stopped
    output wire                    finished,    // ... and the pipeline is empty
    output reg                     ovf_sticky,
    output wire                    alu_busy,
    output wire                    ex_busy,
    output wire                    wb_we,
    output wire [`REG_AW-1:0]      wb_rd,
    output wire [`CX_WORD-1:0]     wb_data
);
    // ------------------------------------------------------------------ IF --
    wire [`IW-1:0] if_instr;

    imem u_imem (
        .Clk(Clk), .we(prog_we), .waddr(prog_addr), .wdata(prog_data),
        .raddr(pc), .rdata(if_instr)
    );

    // ------------------------------------------------------------- IF / ID --
    reg              id_v;
    reg [`IW-1:0]    id_ir;

    wire [3:0]            id_op  = id_ir[31:28];
    wire [`REG_AW-1:0]    id_rd  = id_ir[27:25];
    wire [`REG_AW-1:0]    id_rs  = id_ir[24:22];
    wire [`REG_AW-1:0]    id_rt  = id_ir[21:19];
    wire [`CX_WORD-1:0]   id_imm = id_ir[15:0];

    wire id_is_alu  = (id_op == `OP_ADD) || (id_op == `OP_SUB) || (id_op == `OP_MUL);
    wire id_is_halt = (id_op == `OP_HALT);
    wire id_writes  = id_is_alu || (id_op == `OP_LDI) || (id_op == `OP_MOV);
    wire id_uses_rs = id_is_alu || (id_op == `OP_MOV);
    wire id_uses_rt = id_is_alu;

    wire [1:0] id_alu_op = (id_op == `OP_SUB) ? `ALU_SUB :
                           (id_op == `OP_MUL) ? `ALU_MUL : `ALU_ADD;

    // ------------------------------------------------------------------ ID --
    wire [`CX_WORD-1:0] rf_rd1, rf_rd2;
    reg                 wb_v;
    reg [`REG_AW-1:0]   wb_a;
    reg [`CX_WORD-1:0]  wb_d;

    assign wb_we   = wb_v;
    assign wb_rd   = wb_a;
    assign wb_data = wb_d;

    regfile u_rf (
        .Clk(Clk), .RstN(RstN),
        .we(wb_v), .wa(wb_a), .wd(wb_d),
        .ra1(id_rs), .ra2(id_rt), .rd1(rf_rd1), .rd2(rf_rd2),
        .ra_dbg(dbg_raddr), .rd_dbg(dbg_rdata)
    );

    // Write-back forwarding: the register array is written on this edge, so a
    // combinational read of the same address still returns the old value.
    wire [`CX_WORD-1:0] rs_val = (wb_v && wb_a == id_rs) ? wb_d : rf_rd1;
    wire [`CX_WORD-1:0] rt_val = (wb_v && wb_a == id_rt) ? wb_d : rf_rd2;

    // ------------------------------------------------------------- ID / EX --
    reg                 ex_v;
    reg                 ex_is_alu;
    reg                 ex_writes;
    reg [`REG_AW-1:0]   ex_rd;
    reg [`CX_WORD-1:0]  ex_simple;    // result of LDI / MOV, which need no ALU

    reg                 alu_start;
    reg [1:0]           alu_op;
    reg [`CX_WORD-1:0]  alu_a, alu_b;
    wire [`CX_WORD-1:0] alu_y;
    wire                alu_done, alu_ovf;

    complex_alu u_alu (
        .Clk(Clk), .RstN(RstN),
        .start(alu_start), .op(alu_op), .a(alu_a), .b(alu_b),
        .y(alu_y), .ovf(alu_ovf), .busy(alu_busy), .done(alu_done)
    );

    assign ex_busy = ex_v;

    // `halted` only means the fetch stage stopped: the last instruction may
    // still be in EX, and its result may still be sitting in the write-back
    // register waiting for the next clock edge. Anything that reads the
    // register file when the program ends must wait for `finished`, which
    // additionally requires the pipeline to be empty. (wb_v high means the
    // write lands on the coming edge, so it has to be clear too.)
    assign finished = halted && !ex_v && !wb_v;

    // ------------------------------------------------------------- control --
    wire ex_completing = ex_v && (!ex_is_alu || alu_done);
    wire ex_can_accept = !ex_v || ex_completing;

    // A source register still being produced in EX is not readable yet. The
    // instruction waits in ID; once the producer moves on to WB the forward
    // above supplies the value, so the stall lasts exactly one cycle longer
    // than the producer's own execution.
    wire hazard = ex_v && ex_writes &&
                  ((id_uses_rs && ex_rd == id_rs) ||
                   (id_uses_rt && ex_rd == id_rt));

    wire halting = id_v && id_is_halt && ex_can_accept;
    wire id_go   = id_v && ex_can_accept && !hazard;
    wire if_go   = !halted && !halting && (!id_v || id_go);

    // ------------------------------------------------------------ sequential --
    always @(posedge Clk or negedge RstN) begin
        if (!RstN) begin
            pc         <= {`MEM_AW{1'b0}};
            id_v       <= 1'b0;
            id_ir      <= {`IW{1'b0}};
            ex_v       <= 1'b0;
            ex_is_alu  <= 1'b0;
            ex_writes  <= 1'b0;
            ex_rd      <= {`REG_AW{1'b0}};
            ex_simple  <= {`CX_WORD{1'b0}};
            alu_start  <= 1'b0;
            alu_op     <= 2'd0;
            alu_a      <= {`CX_WORD{1'b0}};
            alu_b      <= {`CX_WORD{1'b0}};
            wb_v       <= 1'b0;
            wb_a       <= {`REG_AW{1'b0}};
            wb_d       <= {`CX_WORD{1'b0}};
            halted     <= 1'b0;
            ovf_sticky <= 1'b0;
        end else if (run) begin
            alu_start <= 1'b0;
            wb_v      <= 1'b0;

            // ---- EX -> WB ----
            if (ex_completing) begin
                wb_v <= ex_writes;
                wb_a <= ex_rd;
                wb_d <= ex_is_alu ? alu_y : ex_simple;
                if (ex_is_alu && alu_ovf) ovf_sticky <= 1'b1;
                ex_v <= 1'b0;
            end

            // ---- ID -> EX (written after the block above so that an
            //      instruction can enter EX in the very cycle it frees up) ----
            if (id_go && !id_is_halt) begin
                ex_v      <= 1'b1;
                ex_is_alu <= id_is_alu;
                ex_writes <= id_writes;
                ex_rd     <= id_rd;
                ex_simple <= (id_op == `OP_LDI) ? id_imm : rs_val;
                if (id_is_alu) begin
                    alu_start <= 1'b1;
                    alu_op    <= id_alu_op;
                    alu_a     <= rs_val;
                    alu_b     <= rt_val;
                end
            end

            // ---- IF -> ID ----
            if (halting) begin
                halted <= 1'b1;
                id_v   <= 1'b0;
            end else if (if_go) begin
                id_v  <= 1'b1;
                id_ir <= if_instr;
                pc    <= pc + 1'b1;
            end else if (id_go) begin
                id_v  <= 1'b0;
            end
        end
    end
endmodule

Assignments/Lab08-Complex-ALU/tb/tb_complex_wave.v
`timescale 1ns/1ps
`include "complex_pkg.vh"

`ifndef VCD_FILE
`define VCD_FILE "waves/complex_cpu.vcd"
`endif

module tb_complex_wave;
    reg                 Clk = 1'b0, RstN = 1'b1, run_en = 1'b0;
    reg                 prog_we = 1'b0;
    reg [`MEM_AW-1:0]   prog_addr = 5'd0;
    reg [`IW-1:0]       prog_data = 32'd0;
    reg [`REG_AW-1:0]   dbg_raddr = 3'd0;

    wire [`CX_WORD-1:0] dbg_rdata;
    wire [`MEM_AW-1:0]  pc;
    wire                halted, finished, ovf_sticky, alu_busy, ex_busy, wb_we;
    wire [`REG_AW-1:0]  wb_rd;
    wire [`CX_WORD-1:0] wb_data;

    complex_cpu dut (
        .Clk(Clk), .RstN(RstN), .run(run_en),
        .prog_we(prog_we), .prog_addr(prog_addr), .prog_data(prog_data),
        .dbg_raddr(dbg_raddr), .dbg_rdata(dbg_rdata),
        .pc(pc), .halted(halted), .finished(finished), .ovf_sticky(ovf_sticky),
        .alu_busy(alu_busy), .ex_busy(ex_busy),
        .wb_we(wb_we), .wb_rd(wb_rd), .wb_data(wb_data)
    );

    always #5 Clk = ~Clk;

    reg [`IW-1:0] prog [0:`MEM_WORDS-1];
    integer i;

    function [`IW-1:0] enc;
        input [3:0]          o;
        input [`REG_AW-1:0]  rd;
        input [`REG_AW-1:0]  rs;
        input [`REG_AW-1:0]  rt;
        input [`CX_WORD-1:0] imm;
        begin
            enc = {o, rd, rs, rt, 3'b000, imm};
        end
    endfunction

    initial begin
        $dumpfile(`VCD_FILE);
        $dumpvars(0, tb_complex_wave);

        for (i = 0; i < `MEM_WORDS; i = i + 1)
            prog[i] = enc(`OP_HALT, 3'd0, 3'd0, 3'd0, 16'd0);

        prog[0] = enc(`OP_LDI,  3'd1, 3'd0, 3'd0, {8'sd4, 8'sd3});
        prog[1] = enc(`OP_LDI,  3'd2, 3'd0, 3'd0, {-8'sd2, 8'sd1});
        prog[2] = enc(`OP_MUL,  3'd3, 3'd1, 3'd2, 16'd0);
        prog[3] = enc(`OP_ADD,  3'd4, 3'd1, 3'd2, 16'd0);
        prog[4] = enc(`OP_SUB,  3'd5, 3'd3, 3'd4, 16'd0);
        prog[5] = enc(`OP_MUL,  3'd6, 3'd5, 3'd1, 16'd0);
        prog[6] = enc(`OP_MOV,  3'd7, 3'd6, 3'd0, 16'd0);
        prog[7] = enc(`OP_HALT, 3'd0, 3'd0, 3'd0, 16'd0);

        @(negedge Clk); RstN = 1'b0;
        repeat (3) @(negedge Clk); RstN = 1'b1;

        // Only the words the program actually reaches are loaded, so the
        // picture is not dominated by the loader.
        for (i = 0; i < 8; i = i + 1) begin
            prog_we = 1'b1; prog_addr = i[`MEM_AW-1:0]; prog_data = prog[i];
            @(negedge Clk);
        end
        prog_we = 1'b0;

        RstN = 1'b0; @(negedge Clk); @(negedge Clk); RstN = 1'b1;
        @(negedge Clk);

        run_en = 1'b1;
        i = 0;
        while (!finished && i < 200) begin
            @(negedge Clk);
            i = i + 1;
        end
        repeat (6) @(negedge Clk);

        $display("Wrote VCD: %s", `VCD_FILE);
        $finish;
    end
endmodule

Assignments/Lab08-Complex-ALU/waves/complex_cpu.vcd
$date
	Wed Aug 26 20:31:03 2026
$end
$version
	Icarus Verilog
$end
$timescale
	1ps
$end
$scope module tb_complex_wave $end
$var wire 1 ! wb_we $end
$var wire 3 " wb_rd [2:0] $end
$var wire 16 # wb_data [15:0] $end
$var wire 5 $ pc [4:0] $end
$var wire 1 % ovf_sticky $end
$var wire 1 & halted $end
$var wire 1 ' finished $end
$var wire 1 ( ex_busy $end
$var wire 16 ) dbg_rdata [15:0] $end
$var wire 1 * alu_busy $end
$var reg 1 + Clk $end
$var reg 1 , RstN $end
$var reg 3 - dbg_raddr [2:0] $end
$var reg 5 . prog_addr [4:0] $end
$var reg 32 / prog_data [31:0] $end
$var reg 1 0 prog_we $end
$var reg 1 1 run_en $end
$var integer 32 2 i [31:0] $end
$scope function enc $end
$var reg 16 3 imm [15:0] $end
$var reg 4 4 o [3:0] $end
$var reg 3 5 rd [2:0] $end
$var reg 3 6 rs [2:0] $end
$var reg 3 7 rt [2:0] $end
$upscope $end
$scope module dut $end
$var wire 1 + Clk $end
$var wire 1 , RstN $end
$var wire 3 8 dbg_raddr [2:0] $end
$var wire 1 ( ex_busy $end
$var wire 1 9 ex_can_accept $end
$var wire 1 : ex_completing $end
$var wire 1 ' finished $end
$var wire 1 ; halting $end
$var wire 1 < hazard $end
$var wire 1 = id_go $end
$var wire 1 > id_is_alu $end
$var wire 1 ? id_uses_rs $end
$var wire 1 @ id_uses_rt $end
$var wire 1 A id_writes $end
$var wire 1 B if_go $end
$var wire 5 C prog_addr [4:0] $end
$var wire 32 D prog_data [31:0] $end
$var wire 1 0 prog_we $end
$var wire 1 1 run $end
$var wire 16 E wb_data [15:0] $end
$var wire 3 F wb_rd [2:0] $end
$var wire 1 ! wb_we $end
$var wire 16 G rt_val [15:0] $end
$var wire 16 H rs_val [15:0] $end
$var wire 16 I rf_rd2 [15:0] $end
$var wire 16 J rf_rd1 [15:0] $end
$var wire 32 K if_instr [31:0] $end
$var wire 3 L id_rt [2:0] $end
$var wire 3 M id_rs [2:0] $end
$var wire 3 N id_rd [2:0] $end
$var wire 4 O id_op [3:0] $end
$var wire 1 P id_is_halt $end
$var wire 16 Q id_imm [15:0] $end
$var wire 2 R id_alu_op [1:0] $end
$var wire 16 S dbg_rdata [15:0] $end
$var wire 16 T alu_y [15:0] $end
$var wire 1 U alu_ovf $end
$var wire 1 V alu_done $end
$var wire 1 * alu_busy $end
$var reg 16 W alu_a [15:0] $end
$var reg 16 X alu_b [15:0] $end
$var reg 2 Y alu_op [1:0] $end
$var reg 1 Z alu_start $end
$var reg 1 [ ex_is_alu $end
$var reg 3 \ ex_rd [2:0] $end
$var reg 16 ] ex_simple [15:0] $end
$var reg 1 ^ ex_v $end
$var reg 1 _ ex_writes $end
$var reg 1 & halted $end
$var reg 32 ` id_ir [31:0] $end
$var reg 1 a id_v $end
$var reg 1 % ovf_sticky $end
$var reg 5 b pc [4:0] $end
$var reg 3 c wb_a [2:0] $end
$var reg 16 d wb_d [15:0] $end
$var reg 1 e wb_v $end
$scope module u_alu $end
$var wire 1 + Clk $end
$var wire 1 , RstN $end
$var wire 16 f a [15:0] $end
$var wire 16 g b [15:0] $end
$var wire 2 h op [1:0] $end
$var wire 1 Z start $end
$var wire 16 i mp [15:0] $end
$var wire 1 * busy $end
$var wire 8 j br [7:0] $end
$var wire 8 k bi [7:0] $end
$var wire 17 l as [16:0] $end
$var wire 8 m ar [7:0] $end
$var wire 8 n ai [7:0] $end
$var parameter 3 o A_IM $end
$var parameter 3 p A_RE $end
$var parameter 3 q IDLE $end
$var parameter 3 r M1 $end
$var parameter 3 s M2 $end
$var parameter 3 t M3 $end
$var parameter 3 u M4 $end
$var reg 16 v a_r [15:0] $end
$var reg 1 w asub $end
$var reg 17 x ax [16:0] $end
$var reg 17 y ay [16:0] $end
$var reg 16 z b_r [15:0] $end
$var reg 1 V done $end
$var reg 8 { mx [7:0] $end
$var reg 8 | my [7:0] $end
$var reg 2 } op_r [1:0] $end
$var reg 1 U ovf $end
$var reg 1 ~ sat_r $end
$var reg 3 !" st [2:0] $end
$var reg 16 "" t1 [15:0] $end
$var reg 16 #" t3 [15:0] $end
$var reg 16 $" y [15:0] $end
$scope function clipped $end
$var reg 17 %" v [16:0] $end
$upscope $end
$scope function sat8 $end
$var reg 17 &" v [16:0] $end
$upscope $end
$scope module u_add $end
$var wire 1 w sub $end
$var wire 17 '" x [16:0] $end
$var wire 17 (" y [16:0] $end
$var wire 17 )" s [16:0] $end
$upscope $end
$scope module u_mul $end
$var wire 8 *" x [7:0] $end
$var wire 8 +" y [7:0] $end
$var wire 16 ," p [15:0] $end
$upscope $end
$upscope $end
$scope module u_imem $end
$var wire 1 + Clk $end
$var wire 5 -" raddr [4:0] $end
$var wire 32 ." rdata [31:0] $end
$var wire 5 /" waddr [4:0] $end
$var wire 32 0" wdata [31:0] $end
$var wire 1 0 we $end
$upscope $end
$scope module u_rf $end
$var wire 1 + Clk $end
$var wire 1 , RstN $end
$var wire 3 1" ra1 [2:0] $end
$var wire 3 2" ra2 [2:0] $end
$var wire 3 3" ra_dbg [2:0] $end
$var wire 16 4" rd1 [15:0] $end
$var wire 16 5" rd2 [15:0] $end
$var wire 16 6" rd_dbg [15:0] $end
$var wire 3 7" wa [2:0] $end
$var wire 16 8" wd [15:0] $end
$var wire 1 e we $end
$var parameter 32 9" NREG $end
$var integer 32 :" i [31:0] $end
$upscope $end
$upscope $end
$upscope $end
$enddefinitions $end
$comment Show the parameter values. $end
$dumpall
b1000 9"
b110 u
b101 t
b100 s
b11 r
b0 q
b1 p
b10 o
$end
#0
$dumpvars
bx :"
bx 8"
bx 7"
bx 6"
bx 5"
bx 4"
b0 3"
bx 2"
bx 1"
b0 0"
b0 /"
bx ."
bx -"
bx ,"
bx +"
bx *"
bx )"
bx ("
bx '"
bx &"
bx %"
bx $"
bx #"
bx ""
bx !"
x~
bx }
bx |
bx {
bx z
bx y
bx x
xw
bx v
bx n
bx m
bx l
bx k
bx j
bx i
bx h
bx g
bx f
xe
bx d
bx c
bx b
xa
bx `
x_
x^
bx ]
bx \
x[
xZ
bx Y
bx X
bx W
xV
xU
bx T
bx S
bx R
bx Q
xP
bx O
bx N
bx M
bx L
bx K
bx J
bx I
bx H
bx G
bx F
bx E
b0 D
b0 C
xB
xA
x@
x?
x>
x=
x<
x;
x:
x9
b0 8
b0 7
b0 6
b0 5
b1111 4
b0 3
b100000 2
01
00
b0 /
b0 .
b0 -
1,
0+
x*
bx )
x(
x'
x&
x%
bx $
bx #
bx "
x!
$end
#5000
b0 l
b0 )"
0w
b0 y
b0 ("
b0 x
b0 '"
b0 i
b0 ,"
b0 |
b0 +"
b0 {
b0 *"
0*
b0 !"
0V
1+
#10000
0A
0?
1B
0@
0>
0<
b0 R
0=
0;
b0 H
b0 G
0'
19
0:
0P
b0 O
b0 N
b0 J
b0 4"
b0 M
b0 1"
b0 I
b0 5"
b0 L
b0 2"
b0 Q
b0 j
b0 k
b0 m
b0 n
0%
0&
b0 #
b0 E
b0 d
b0 8"
b0 "
b0 F
b0 c
b0 7"
0!
0e
b0 X
b0 g
b0 W
b0 f
b0 Y
b0 h
0Z
b0 ]
b0 \
0_
0[
0(
0^
b0 `
0a
b0 $
b0 b
b0 -"
0~
b0 #"
b0 ""
b0 }
b0 z
b0 v
0U
b0 T
b0 $"
b0 )
b0 S
b0 6"
b1000 :"
0,
0+
#15000
b1000 :"
1+
#20000
0+
#25000
b1000 :"
1+
#30000
0+
#35000
b1000 :"
1+
#40000
b10010000000000000010000000011 /
b10010000000000000010000000011 D
b10010000000000000010000000011 0"
10
b0 2
1,
0+
#45000
b10010000000000000010000000011 K
b10010000000000000010000000011 ."
1+
#50000
b10100000000001111111000000001 /
b10100000000001111111000000001 D
b10100000000001111111000000001 0"
b1 .
b1 C
b1 /"
b1 2
0+
#55000
1+
#60000
b1010110010100000000000000000000 /
b1010110010100000000000000000000 D
b1010110010100000000000000000000 0"
b10 .
b10 C
b10 /"
b10 2
0+
#65000
1+
#70000
b111000010100000000000000000000 /
b111000010100000000000000000000 D
b111000010100000000000000000000 0"
b11 .
b11 C
b11 /"
b11 2
0+
#75000
1+
#80000
b1001010111000000000000000000000 /
b1001010111000000000000000000000 D
b1001010111000000000000000000000 0"
b100 .
b100 C
b100 /"
b100 2
0+
#85000
1+
#90000
b1011101010010000000000000000000 /
b1011101010010000000000000000000 D
b1011101010010000000000000000000 0"
b101 .
b101 C
b101 /"
b101 2
0+
#95000
1+
#100000
b101111100000000000000000000000 /
b101111100000000000000000000000 D
b101111100000000000000000000000 0"
b110 .
b110 C
b110 /"
b110 2
0+
#105000
1+
#110000
b11110000000000000000000000000000 /
b11110000000000000000000000000000 D
b11110000000000000000000000000000 0"
b111 .
b111 C
b111 /"
b111 2
0+
#115000
1+
#120000
b1000 :"
0,
00
b1000 2
0+
#125000
b1000 :"
1+
#130000
0+
#135000
b1000 :"
1+
#140000
1,
0+
#145000
1+
#150000
b0 2
11
0+
#155000
1A
1B
1=
b1 O
b1 N
b10000000011 Q
b10100000000001111111000000001 K
b10100000000001111111000000001 ."
b1 $
b1 b
b1 -"
b10010000000000000010000000011 `
1a
1+
#160000
b1 2
0+
#165000
b10 N
b1111111000000001 Q
1:
b1010110010100000000000000000000 K
b1010110010100000000000000000000 ."
b10 $
b10 b
b10 -"
b10100000000001111111000000001 `
b10000000011 ]
b1 \
1_
1(
1^
1+
#170000
b10 2
0+
#175000
0B
0=
1<
1?
1A
b10 R
b10000000011 H
1@
1>
b101 O
b11 N
b1 M
b1 1"
b10 L
b10 2"
b0 Q
b111000010100000000000000000000 K
b111000010100000000000000000000 ."
b11 $
b11 b
b11 -"
b1010110010100000000000000000000 `
b1111111000000001 ]
b10 \
1(
1^
b10000000011 #
b10000000011 E
b10000000011 d
b10000000011 8"
b1 "
b1 F
b1 c
b1 7"
1!
1e
1+
#180000
b11 2
0+
#185000
1B
1=
0<
b1111111000000001 G
0:
b10000000011 J
b10000000011 4"
0(
0^
b1111111000000001 #
b1111111000000001 E
b1111111000000001 d
b1111111000000001 8"
b10 "
b10 F
b10 c
b10 7"
1!
1e
1+
#190000
b100 2
0+
#195000
0B
1A
1?
b0 R
09
0=
1@
1>
0<
b11 O
b100 N
0:
b1001010111000000000000000000000 K
b1001010111000000000000000000000 ."
b100 $
b100 b
b100 -"
b111000010100000000000000000000 `
b1111111000000001 X
b1111111000000001 g
b10000000011 W
b10000000011 f
b10 Y
b10 h
1Z
b10000000011 ]
b11 \
1[
1(
1^
0!
0e
b1111111000000001 I
b1111111000000001 5"
1+
#200000
b101 2
0+
#205000
b11 i
b11 ,"
b1 |
b1 +"
b11 {
b11 *"
b1 j
b11111110 k
b11 m
b100 n
1*
b11 !"
b10 }
b1111111000000001 z
b10000000011 v
0Z
1+
#210000
b110 2
0+
#215000
b1011 l
b1011 )"
1w
b11111111111111000 y
b11111111111111000 ("
b11 x
b11 '"
b11111110 |
b11111110 +"
b1111111111111000 i
b1111111111111000 ,"
b100 {
b100 *"
b100 !"
b11 ""
1+
#220000
b111 2
0+
